{"meta":{"builtAt":"2026-06-10T21:59:41.949Z","source":"local","count":2399,"model":"Xenova/bge-small-en-v1.5","projector":"umap-js","umap":{"nNeighbors":15,"minDist":0.1,"seed":2654435769},"relax":{"iters":200,"spring":0.02,"push":0.6,"perNoteHeight":true}},"coords":{"5nbtzQeFa9DcF6Kpw8KRdN":[-7540,-15905],"4XBuX9D6GquQcA6dkdGBfv":[-10214,-11519],"jpnyfjFu2hs4qwdQm8ESxL":[-7787,-14587],"6CacncJW3xd1YpXg2ZGMgM":[-7441,-15801],"e9owmDPKMFK9FPUsvaJLb4":[-9224,-11657],"gqXnTuzJKxcmtoEQEaGAfM":[-7899,-15687],"n188aWqdJx8kSfwjphxejN":[-15031,570],"5u4cK85zJkbQoZruoBkSGc":[-13731,2221],"jHsq6mD1vDXzeADAuazU9d":[-10612,1375],"4Zzy5RNsjoPriYfrexygL8":[-13244,-6562],"7DHtEXaWgmVWFh9j3AnAZZ":[10680,-3735],"oX4gPdqPQJN8rQu3Qmf9uu":[-10106,-10712],"tHTfT3EPQE1mCPkzuiZ6mW":[13324,3102],"v9De3c8n3EZoxJhuu1GQ2y":[-7892,-10440],"bh7FqhufJKYXA1r7B3anDH":[12988,3613],"hesjttRRwewAT3bToaRZTk":[14324,2174],"q5KA1hBJMm5KqKoGX8mbFz":[-8479,-10721],"uvwzGUmnJNnmvxQA9YRaxp":[13967,-3056],"qQVtu6QgP7MCZ8j5npkS9G":[16238,707],"r8mPdZJdNuva16CKEvNMN9":[-17329,4482],"wo3cFa82FR1Nu57uHjpTg6":[16453,-966],"3eCb2WFnG4gLYzECeBBzrw":[-15130,-389],"haR8cbJJLUo6k4nVQBySiz":[11372,-1831],"dPrXWXctW1nvhziAqUd2JM":[-5454,-11210],"gWuraaHSGxTBYVMErVHCxd":[-5272,-9948],"jk5FjMMpFisswq3UjyAC8m":[-15231,-4008],"rhGPiDCQoxUNRBPAAu91vJ":[16538,-3123],"qMGFSVUXnVox9E1RAPVkdi":[16418,-2971],"icozcjfYPZVFF9aehXSR7c":[16789,-3261],"kvbPdLcwZnJnPaV9vy5SLM":[16745,-2964],"fTGnkk9XiGMuWyxiefrDDz":[12623,-7873],"rfBrsnKcwdr1hYtaFUDYqQ":[16499,-3467],"6eGHQdriGJLSpbEyyDCq7Y":[16736,843],"ubZso7tRJo75avoFbK54QR":[13138,-1086],"v9opfgbadogntsQqMWhRGn":[13722,-680],"sPNAgekhZbPYe4k3dCwCxd":[14086,-4349],"byNQ39Dkci4YGdJD67tyVo":[-15563,-3200],"hoteeymo4fmrW4Ljkmb3QC":[-14000,2075],"e4x1A1r5VYQHTcU3ryzYq7":[-11964,7362],"fnNNSqTRZNjivD37At3E3Z":[16073,2498],"sN9hcEeiBEkajzLy2cyEq5":[-13004,-2421],"qt7xNYTHQDwFzm1xGznXKM":[16237,-3117],"hN7ee1RPaJ1FmdHMwk7t6R":[-16557,-1655],"tmpk6jWxyDftCFVXs98oGv":[17364,-2395],"hwEs4ghjEZFqqb7ZRXA7DG":[15982,-3246],"tPYsd16Jo7FRs5aCkrNMqE":[8897,5913],"x8DW5K75rjEgxi9678XRnd":[15879,-3639],"sFZtDXaNvcypwQ1YysFJPY":[-11609,3469],"h67x1FdgNzay1YpM39ffqH":[-15651,-2876],"rrqXPFfFjcjJwazzoGbf7L":[-16316,-1996],"rwEVNQkBKS9K2r8GfqSKTy":[-15525,3549],"deMmkRfoCpQh4xmiXYAw5h":[-336,-11893],"qZxNxZYUn7QS5erAzomXmT":[-14059,3416],"2V2ReoE5hwoUuFmkzDvu1g":[17868,-2088],"1JxDCVb31kPLGtMkEgWfaK":[17855,-1507],"jCr35dpShwPznXgEhsmpT2":[-7239,-17258],"rUbHPYzHZsrD42u8c9HdsC":[-8250,4206],"2eVr8qsucZcXjC7N8Aqok4":[-7767,3546],"cYiVUFFzhrgCixNZQCcyCX":[17061,-1915],"pQm38wZFYS7DPrHJ1C9kyb":[-145,-11087],"ozMiepSPQ6HLnEaHHW1QXi":[13,3348],"oT7zMvbdFmu5mgNm9goaRp":[15185,-2121],"3txg5xjuoUsJWZ2BLbDPMN":[2481,5225],"s3cMsm6Tzc3BP1NNWJ6Bhs":[15738,-3507],"9MZJ4R2PjYHA6YWqMczwRo":[-15431,228],"bgZWTahX4cDX8a28LuHGkT":[-3746,4195],"9HysdnY9ePkU1GfMRaPryy":[16086,-3491],"9J1PmGW8GSxL7uB2adCnx8":[-4317,6279],"sf5AsCx4VfY1drgC1E7STm":[-14974,-3681],"rkP3NXEy7PQ8gXU718BBvn":[-15350,1511],"m1CBnKmzhy2obGhuJFY6cW":[-4779,-14447],"tC2cgQ757GULHthcdWJbmT":[-16143,-883],"rkhZdKKDxtLJ6n1X8jemyY":[-15997,2466],"eGdecQbftb5SKX1ZiV2mjV":[16043,-2024],"9F3xMcDsinp44ddzQDGDQa":[14626,-1055],"todE6Paffy6pHKNX91DvmY":[10479,-1678],"5eLTTRZk55hi7Vpnr7zhFd":[17320,-2271],"3gj1nRrMQT3U1v1VzoSMFY":[17315,-2530],"tpFLJQUwjdY4WSwni2F8cP":[12696,5233],"3gQnRpJZaHqexfJJzXhpMg":[-16321,3601],"7j37UKzBbDQsymoP1rVXPu":[-11185,15495],"gJNEH2dgyPzJFifybbcWwp":[-4527,-12872],"uRnFwkzK8u4AVQihTEjZ6r":[-15393,-3894],"i3omjQH9qPPKLxWh68u7E1":[-17449,-1643],"dzxK5wWHwB86soCAxpidBu":[-15006,-3868],"5rgNdTPqwAbpb2xmgxr9Zh":[-16416,-664],"wF821BhRfV9wLxwiVobKRk":[-16086,-995],"68c6ckeeszMGXrhZmkyEHn":[-12814,-270],"1RKrCz1TtdxELFjv2HimvG":[12873,1345],"gNT87yV5jnqeaive9UYimC":[-16032,-2226],"1zty3kEuQMbAspSBDZMgX1":[15852,-2751],"obqBaJnmKBvNZNR7iXrpqh":[-11043,13820],"hkn8ASDnPcbwoMniesA7WC":[-14397,-3727],"miGiAfHY8XNZwXAicHENG8":[-6931,-7931],"hNo2ZUT482gr5bXG9QJXCa":[-5017,-6533],"c2V5zTktcCgpoVvv1czt2U":[-14073,-2106],"tagyvYvA8ahw4FkD33nAAq":[-10349,16060],"vKhNCuxDWjaGbwzFQ84YUm":[-13575,234],"duc66aJfmn6RsFzgcsyYRM":[15729,-3093],"g7Vbt1PERjS61TPBZcwB98":[12392,-5259],"fV9cBSUfYcdcuZxEWMnbch":[-15130,-2355],"8R73GvV3YfX44GhRYe8Bab":[-17303,-1767],"bmFgHBpxcUF6XMoQpvd6KV":[-3757,-10859],"3MdiMf5uTNmKuabRZWmfbv":[-12818,-2311],"u8xe9sXzY3SLA4k7Htgjzs":[-7266,-16960],"vi16GwnJo4kgWMHTiiAAUF":[2898,-9850],"iDshQ2tktwysgqGSbXv3bh":[-15275,-3712],"a1UQC5RLhTaoNb9H5FouRf":[-13259,-2769],"hNnMMBe5WqMBrCw8iqJbc8":[-17000,-1769],"nkfNdt6a4eB8HE7tAJitzr":[-15988,-2842],"bRuegdyFUpSnPNFVB89tWZ":[-16403,89],"qL8ibNjoNrEXZU9ux1Gxes":[-16990,-932],"4JUTrp93x4fDDJyxdXNJdy":[-17148,-1652],"4e12MjSx5RQrT6bQSfiaqF":[-14792,-4567],"nCwCNBWX6Q1VWzAH2niFN9":[-15869,-3431],"pTdKKBaRE166hsucGSUsni":[-14050,-3653],"1AQaQc6woFUeWo6Y4KJbyQ":[-16532,-2229],"kPu1Uq6gzhbiQRbNYgXwDm":[-7722,13178],"6a2TqZdjH9fsawbnUKbUe4":[-7362,-16170],"diqmJQxkcuAK4C3s8yC3zm":[-2384,7021],"tWYgESvaZSpp2EoSo4oQKf":[-12382,2629],"wSKgszmfJUdvW4PDNssaq9":[4280,-9715],"7eR6aJ6KRKmSg4Qvg7grZw":[12090,5081],"pHTWiEZsat6unniyx1TfjR":[16485,-3259],"k2NCChDr12UjkcMwF5rCmE":[16740,-2648],"nrGMU1xgoswjGtekhFfPrj":[-5496,4429],"coGjpq3YydUADUsHPKdi3D":[15041,-3045],"6KZw2kn7KpDBnqmi96pxTY":[-7713,6960],"3dtdmguDEjqTp4iokHQmht":[-14489,2475],"54taUfTzTNcprwyYMV8Swd":[-4997,-11595],"3jF2xzKqCspD1b71EJPpe7":[2641,-11472],"5iLsn7qPeFB5E5KtritWvv":[2916,-9673],"eRcTUH7E2TxQej7BLqdU9B":[9891,-3362],"oFeDyxYi2ZZqFLDuU8MbTT":[14119,-2170],"5RaTnXB6hRJYqvJLJEfYU5":[14603,-1682],"cvnjfTkG1Q3XX9bTkqkwCW":[12055,-3091],"gRVQD5N6zCWSYSCE3nPkMR":[3071,-10807],"tTvQNxh51zQGSWr4rdeEWr":[13485,-257],"rcCsYJ5pa69tG5nsnfoVqz":[13784,-76],"bB53F1SoemsWhVMrken6N2":[14891,3515],"gkXTLpL7bidJHEa1f1vZxs":[14417,-1886],"kaftKTrbn38TEMYjUFBFSo":[13125,1163],"aFaAXYC2XdqG5uQz24Lhsz":[15243,-3245],"usEWSAZcfXG9iS1XM8gy4g":[15069,-525],"hNkdABumRVHQz94HGjQJpe":[14250,3042],"fjnxp7n4AMn9zEwwoiAcu9":[14829,2257],"kNU4JtUtpUgWbQysqT9xh1":[2730,-8459],"5iQFE9QK7HG3diQQ7c3YMw":[2540,-8643],"2tysaXaMLnv2Cvhq6NiLiq":[2604,-8836],"2XLKzArpDK2D5nk3JDDQCc":[15025,3229],"88D5CTysTGVLwGareic3Tm":[14720,-5075],"fZjqdMo6YVDMireykNBehx":[16079,-296],"bztkD1L3QBrYBQ6DxFzXPj":[915,5109],"7GWm4et3xnYGMnpszZqZVF":[-14930,2578],"r3NQCvh3nNRZ6XENJ8LaUa":[-10270,5603],"uz8idD8QbqpVe5WKoVQhY5":[4210,-2518],"av9yZE7q72dUyQf4Lz7TWQ":[-15944,-1489],"nZbWC8FwpX7TbRRx41Ezs7":[17842,-2278],"sE4b8DnQRohA6Wz1MoH2ct":[-5457,-8707],"iNTWf8uQeq8krfwQ3zcMpT":[-5478,-8495],"ptHz2CpSbbfNGSaJAduikr":[4016,-10511],"9PVthBrrkT3ezS9R5PBku4":[72,-8752],"1wyrRDXP9Rfi4az7WApYZ7":[-215,-10199],"dp3U5fnyNsA1bRmABveq9h":[2174,-11844],"3aLLg8aHEfMEZ4oma8x8RV":[-5779,-8514],"cPK3DbQ6AV6P6tVvfgDwzv":[-3732,-5870],"pWdXWoHk12KqWziob5RpWQ":[-4047,-6130],"uq38bXUv3dBX3t3stqcpsu":[-8956,-11125],"1U9iJuLkuRCR9SnnGzvjmB":[-7150,2507],"cxi7HJjm8AUdAqX5ar6VqM":[-5153,-8645],"iHRLardyjGqT9ZFD7DJW2i":[2172,-11973],"ixV43Vzsu1TruvfAk161AE":[-3325,-8152],"ampJL1aj8oHp3ekSNnedsQ":[-4001,-4926],"8kLQxYfoSLSsBTnrFr7J4y":[7252,1361],"2ttWd62exbKTdijBimguVK":[17119,-2123],"wbV1tXHojnzhNvtp64ALCR":[16839,-3111],"8ZfTp7NwZEf86cUPfhaqpM":[14753,-5240],"q5vWAnoUXsVEULNS7WYe1A":[1134,4948],"fHSvFPRzwaqAsXM7Hf8NeA":[-8703,-8494],"ovVFJ6mks1YqDhi9M5684v":[2134,-11706],"ntzthyPjTNhKzVhv8pv1Rf":[-8138,-15334],"tVAstFY8PWDE8GEUoPxZzy":[173,6282],"fdZTxfyuuNhNAFz3J7RNGH":[-9371,-3577],"swzV3Wp2Ay9ZDn6Lxr6He2":[-9415,-13626],"hyeqa4w5MAMog5UBWpsNwv":[-1185,7299],"jFYPW6NBat2NuHCpZtGjyV":[-16779,2309],"rWYQiwz8YjL3nmgSbdSERq":[-11604,3256],"wgpqRKFzX37TwD1TurWUQ1":[892,-11829],"cJubfM7w1ub6rKv2X3obUn":[-16855,2803],"qyPaYp2iXTpZDDRvDgz3R6":[-16106,-2112],"9DF3EjkLNHTqkpjCBYNeHn":[-7248,14194],"i85y12ujZoiVfjTuKrVpAy":[-14330,-158],"mZrvLmnHzETFaqUXiXdqou":[-7075,14462],"iQkg5ts9uHNzjQd4rWCETp":[17192,-1217],"jgHRdonBtUjuY9ThD3Mfpu":[-6944,2643],"2Ht1jFcrzxdtERdZC74mYT":[-15493,4224],"oSR8eE7YQMt1pGjT9xRqxY":[1444,-11902],"rhfMtU6HJs7bfNVZN6naaw":[218,-9504],"p3H1JnqZ3MVDTMeGpNW1if":[-2098,10869],"jtZr3JssUQqVUpqjVp1pxT":[-5177,-8498],"6cEuY4ttm7jnwVBDaZoj73":[-6732,12718],"7juu9FiMurP6GEdYGX4v1u":[-12592,-7223],"2JEtW4iWtrCeUjZPXk1FFX":[1044,-8568],"gAQ2g21LVDTvJi7wusdHVb":[13765,-847],"uFC36WNJ53rijvo6FUogij":[-1054,8343],"mdXvqHvTJjs9brWRzZUeuK":[-10349,-11334],"1NeMhTYoMCpDP8vywkxDwx":[3681,4295],"3kmxXEbDwUE3pctaaEDV6P":[-1928,-11432],"oQutomL8dfyAmnxi2FZxw9":[-1930,-11316],"uLVNzBsYTgKXamWqz4JTAc":[1503,-11787],"oCNzmk5rzJYxJqJ1Ar3U9J":[-15139,230],"5MKFhuJLdKcNTD3w7xni3i":[-12398,7798],"7KWGBhLK5PPxHn7YGw7dqu":[-7693,13300],"mejR5k9Me1PknM3XL1583G":[-4738,-7308],"51zyGqoSfHLwApvxJhHrYu":[2308,-12820],"jc9aj9vLsrChVSUyxmLFaN":[2088,-12621],"acS49j9TjikYBvHDMSAhYA":[-7894,6750],"gx1vqqNqfF58YGtk6x9WJN":[-10893,7765],"dpWKpmMTz8TfAQeuWqZwsV":[4943,4734],"wjk7U9pyvPzuzZ3vRFsE3W":[-11676,3120],"uJFQG4xJXtCmbdtrKWN97s":[-2110,-8914],"irfJ88BXQjcQ1L3cxQMcka":[-1313,-12026],"4Cw7UUsVXcKZvQoZhQiZTf":[-12124,7879],"hCZw5fo2jK1W9jupdpVYSP":[-11564,7580],"nohHmtPa3qqLJBmzsmE6jj":[-11852,7966],"u1QhznJvm9KeKTtex2Rxpf":[3514,3139],"iHvxjoGNdENhebNvEJEFQL":[1724,3297],"r1a1QckQ7Gas7bkCGYGG9P":[268,4351],"2X7pW5YNH88BsJs7p6odr6":[-14325,94],"7sWb5D9RHzUUK2Eq29Dygm":[394,7887],"18CoKYzcgme9mJRKaxRiP3":[-412,9673],"vNZiNjZPSTeweWfkoNahdu":[4054,8122],"kTyQt1Nes6RfkLhtRzL45L":[-9541,8484],"9PPuVRtdozKp9kbiHFd2FC":[1579,-11385],"4h6tnQQoSSELhmshMEmdUj":[-479,-11588],"cwUsGL5i196yCbjzjQrTHo":[2034,-12423],"gwBV3V8ovYrJfJ8uQWzoen":[12463,-540],"gD7MkLskGwToUXyGPLGnQb":[15714,2245],"fmwQPPa81nywv6zayKh7uA":[4113,4047],"aePxMQBes6uxEhGdbZo4dJ":[16274,1977],"fjt1tYze9zJYU9ZMB17daD":[6389,-825],"kMQXnyik4q7vS7mUh7WcNr":[-1415,-11038],"kSCfoztdwFmqfxKwn5BTyM":[1638,-12194],"vhyBctqeStvWgqwZSfkUYL":[-262,-10835],"bRT9qXunfaYodgFvDwHJHU":[16629,-2807],"cfBLRFzXY2bvfSxKrEJ43i":[-8368,3446],"w81vHzgdoNQsHdXEzxYHXP":[-6865,9740],"9upoSNoXaKZV5T17w8txBe":[-505,-7232],"axSHYhPtui7gLYARkaMPzA":[-7495,-13929],"6Z1pmtCZhuv2QdnWmjcuFx":[1664,-11657],"r4BMw7YouZgQs7r4KeYSa2":[13460,-1002],"tMTqinfBtcVb9iN812QMMZ":[13663,-2922],"47cj6p8pTcu64sqmNCjXYE":[-4235,12249],"dhM2VM2GXNbrMTxC4bQHxt":[-7401,13688],"oySXkMEGC7JZkmznEh6DMt":[-3714,15550],"rr8tQNZiAdjGTUkCS2iDBP":[-8763,-9327],"rYn8bzchvDKByVEBo9T6hU":[-2843,14214],"wSYBfHcoX3z2bWNy3DCDVi":[-7144,13499],"2bfU3xagX2AZChzT8K78JH":[-6055,-14359],"g9CVMauCqe2yGvd4xMvprd":[7179,1739],"qumRCb6ApdrM7NSY434yzx":[-5269,12385],"36syzXE2S4Hd9abmuwCrmc":[-4585,-5737],"2oWEmpUBch8YTqXnbB75en":[1478,-12362],"u74VHxxEvt6ExZMscXtPtE":[-8250,11548],"t1WffY4qENiffMxJwXUd1r":[-7152,-10776],"bNMq4Z1rgXLKKn3EJbD4tQ":[-15511,3705],"2Fva5QoVdA5PyNd5w2JGqK":[-9475,-1584],"4WqkQL1yYiF6m1dfL1sKRp":[2305,175],"dXHpqPHi6WNntY9RM8vGCZ":[-5924,8366],"xpWz26HHgJcAtKfiSsrARQ":[-16120,4806],"dJ22aCBZZPNii49KCJUu82":[-13557,-1806],"3PH7A1eLWUK6CP6rreAG6J":[-16409,-2115],"uc5nzZLbMP8WUe8zZsaAP1":[-10226,5717],"5TFFxUrWi9y54XHL5KQFyF":[-7677,13615],"uTCPtkSTgERQGbRMUYaJXi":[-8033,-12690],"osCPnsXA8v9F1rdFbyb6M2":[-7477,-16676],"wFkbKAcVfpBvts69QpZgLH":[-4288,-9624],"cNv8Di48wsdEs6KxF7FpvM":[-4702,-13412],"oSnnWgfXzuToYU7txdUe2n":[-759,9570],"vZ6kg422XbVK5cBRnMQNz7":[-8824,-14244],"fYtRhzcFBtstpTkjhk3AZF":[-6261,-13210],"1VxmamAYGMEC6tXcTnXTLq":[-5833,-14109],"h9A4f8hb3pqY19Nr7ysh6v":[397,11924],"5pMHes1sKWwrABowsezip5":[-6735,-15556],"mw99QSHxjrzNpX2eLpmg3e":[5898,140],"du1v7tLce2EEt7tcNtUYL8":[6833,130],"iViwcnAPdfYmwsHWdi3tiM":[17732,-1153],"e5nZBVwLRv1LzsQzpVRE2e":[9316,720],"hdZatd3zvQoWtA8hGKQJuM":[5159,411],"hiPFNKxkG7r1fp794bCi9g":[5018,2257],"717ipghFYAfnwzc3BmZ2vE":[-12483,-713],"hugFbV22fRmmABeqSkKMNL":[-780,4968],"jjUwQ6CdEA9pSQfef1P63c":[-11053,14742],"inWxSqhuZiMYKAWFd9WaXE":[-4655,5081],"3fyLWtvYQhyFJMfdhqe4EG":[-7084,4669],"9btZmq6XD29TXX54NfDQAg":[-5496,-9801],"mV9zsAWtPZ7ATyG3cVnfF4":[-10042,-12380],"2e2nJsYifh1dnEfLuy4z8d":[-7618,-14445],"vUHsN5dcc95i1oMyhNvsgm":[1447,-12035],"unaU3MSzaJoxXms6QSG21M":[6651,1908],"xcHqe9UB3AWN1qqEdD7a7n":[13670,-2417],"rG2krBbHLdECvUBgYtwfHq":[13597,1902],"8QGRwLbWjaQPBycZRyTWr1":[-7395,14445],"gP5QtVzJQDocxXKcPei31V":[-188,-10447],"ou6CfZNCQydpFpAe9eb1Wa":[10946,-5608],"5e8214D76LPXhtfrh5VXvu":[269,-10424],"mRo5nQpzGpQ6NEUC9LkbgB":[-14757,-141],"fxXugdAELAR4t3FzVp6rMv":[-8381,-8415],"pGrDXvyyPkEYspCxerADBY":[-8297,-12163],"3x5mTt1FQ9sYzE9audDvUx":[-12562,-7509],"baSBSSBumPJmQi2GBvtrJw":[-8336,-12555],"eG5tPJ2JPCXat8WBirfyFn":[-6221,-13914],"apWg3zVuZnTaaDNLJShK3B":[1567,9848],"ha4YJo6FjWXqq7zJFCTsMT":[-12548,-7363],"hTFwsxa5tGtDBXD5fhnVyR":[-14415,-3582],"xxLjTRT3vnLLzzgLLaZYp7":[-12248,-7494],"xthFf1A4Zbei2g1Q6sDr1Y":[-7710,14646],"rN8LNbCsyzNpxuipGbF9Q4":[-6433,12739],"5DcPdk3gyAzAM6ErKRodGM":[-14515,470],"s11DZRNnPT5fBXLPB5y3ou":[-14580,891],"3hudYSUgq8DVy4aMA6JpsU":[-7697,14310],"98xqG2maPihxGsqZdt75tK":[15423,2356],"g8fGXNHgHVT5WNQr9LAy7H":[-3899,14817],"nD5nCbri22feQh8J4ZBzXk":[1334,-12202],"eZTNixXqHUK6tHMc9WwSQU":[-6158,-14028],"cSbeEe6JroEpjd2aBzwUfP":[-6309,13983],"ickZjs5RB6GAwaaFCD81mp":[7236,1486],"6AZoWUBymMooSBZe8QCy9z":[-6314,13825],"jFyihEHJjCmLJnq1nXciKD":[-7336,-16323],"4zMN1d7a2Me51TooSoDbGY":[15771,-3372],"8KXmr4hDvt3VATkVgeDHei":[-12991,-7489],"mSJBDcmUjVTGRuUaBZL8GF":[-318,-10689],"rz8PSvFtHKxRhBQHtJQfyA":[-6328,13179],"8JZRRAH978ae8zodyLYj2N":[311,-9986],"mdsZYtCA7aKQZMLcvGQfuH":[-459,-11062],"hiedR49E6mqWa87ePbyxhG":[-5179,12757],"g4HUxxJTqHFAh9BbAuVkTC":[-7618,16534],"23j5DtnrK9b1v4MN2mvxDX":[2343,4391],"jKxygtTnHzCPoCq5cJDsom":[-5627,13148],"3eGjBjtLNGWAbyuwj3jZWc":[-10273,-11999],"poWtVD5teqbFFrCDi3H4gG":[-15391,-814],"43iLxVuqEH79p4cDqFvNe6":[-1435,-9368],"aus9BAAp2FzEKGaQjxNHLK":[-2296,-11740],"sz7a7uikH7B7Szzq5Zy8AR":[-4944,-11757],"8PfMk9iVtfNeHuMKEGyKSz":[-7419,12772],"twz5uqXQyu2w7KwuPrwMiU":[-1092,-9048],"oJdbKG1ZJhtHCmPgdS61Xc":[-6602,14033],"eKUBuW4TN3AsAFv1zLSQst":[9439,-5192],"b6oTFrAADJefvU8TtEmLNn":[11676,-1521],"9485KTd4YMY2jiFA5giVxi":[-206,-5911],"pkyQSzirPvkuyEtZBbsD4V":[17445,-2111],"kW5sHNwMtwgoDr4PhMqywZ":[-10709,2870],"63nNDWBvct57CC15j5N3dA":[9892,-3821],"3maLhTXe8u5V2uSqWZd5H9":[-9221,10650],"nTkBk6qNF6wFXbTEJoLpL3":[-5993,-13084],"gZwBT8gZNAgUj11JyyEQoR":[-4800,8037],"m4Yq38PstN1eXrKSRKJJdD":[-8175,12700],"hs39eTX4G5YEwohYhP46cn":[-12293,3387],"sDJ8ZxgeGv9ESjmCA3AFMY":[-7071,11615],"einyvRpsQDQ4fk41qf47kr":[-7633,8130],"aUdWnfiS68aF2TeLWCAaLN":[11444,-5081],"mmyUDEWWEy13WnahbN4LCC":[-7137,11934],"uN68RGaQjnQAecjXws1ZY2":[1908,1977],"3Sdha2uV6bQfFD6DjykXhK":[11845,-6082],"wvxc9L4bmj8d6k7yVYwUD8":[-7285,-16483],"bwWs3EsaJ2KvU7XKqwraLf":[14509,-2997],"9dF7YfFGhEygWTnTTzirgc":[6769,-1849],"4uoQQubtUaYhGcv2xpXzgy":[-3166,1157],"rKbpU9r3UqDufKWxCN3nif":[12981,-3960],"r8ciaZQ7yPZDRCzyn5WRQ1":[9505,-2840],"wXcmKmNpfBQLCdE3V41zRk":[3789,10949],"rjWWsApsjJPqnq8hWd2Nap":[16178,-1126],"qjVRco5LAndMckrryG6nr5":[16662,52],"4UKZLVCS75ywcUbY5ijhz9":[4715,1512],"bEZUDAivDHUGmR9GTqw1Nj":[-6885,13936],"1arALhnsXXEVgXb5eZ5bkT":[-133,-5558],"bUdQ66qoS93WFQVzvWkzt9":[-6625,15548],"1UmAsQFiM4dtmGvmj3x6PS":[-8363,10059],"tAZwiZTJQAXkVk4JRNjhbS":[-12353,683],"ia96N7SacVbPDWeTEAnYW8":[-6609,15912],"2xm4xmE6hgo12hJJ6TyHwm":[14553,3041],"bm3VprkgBaZnAUYfTffx5o":[-3108,-12129],"4bMD8KiM8JP5uVbTEJ4GXC":[11111,-5063],"qg72pdYktWRm7cjkraSZEE":[7920,3707],"7zZUukM41RCSoCv5ZtV6c1":[-474,4193],"iaZ1USBHtWXdwUztPahsTt":[-16219,-1783],"2sba5BDmpXJfk8twuajxB2":[3618,5559],"njLxtJjiw97HjZAWmmuban":[11076,-1508],"fedJBogaYepg4aPoxjvxdo":[-8661,13120],"iHE2ZtzLAh9XTHHmJQpZjo":[3995,14141],"mKUfx254Rdrya6uxjf6AcY":[-1303,-8437],"hBURYwSomWpoaWo7BU8VkC":[-7685,-16319],"2XuyGjqG46VDV68H8Nrqhr":[3360,1054],"1t3TMMB4WowadH2G9vUAVD":[-5281,-6338],"9tQJBWb7xwH4SgDm7hmZJM":[-5196,-6225],"dDqXHd5KNzDezcCtbvgAa9":[-7909,-250],"rgCMwbwYhqGacBh9wQouaU":[-5807,-7516],"ogSnsN64MBa1bduSKDRHu3":[-9832,10980],"6Kr3KqhsQyGoV8866jSF6Y":[-1711,4500],"wcvpM4oF9PmmN4YXGcEhN5":[12671,5818],"u5GPu13rPeiTqfPqQXaH5T":[-15140,1211],"895jTVJWMnsdp7Wjucp6yr":[-8686,12232],"gGZGX7JFkh2SqMLYg7cHDA":[4284,-4239],"8oyfR2D5tcaUc5Xi5VXdnw":[-728,-6659],"xaXPmNCTuTYEssNJipBxMr":[-13717,1759],"ku69YGV25vRrfamqEgXJyK":[-1511,9279],"oi7uEk85mxqCEMQxG6XQq1":[12590,-3589],"ksUEf17NTS7EVQN8stq1RH":[-5540,15375],"nphwrUDmcwq2sjhFBLUv4h":[-584,11183],"jjZ1H5vpMHZfRdn4Keixmp":[-14288,5287],"bcwhwJFVv5zFfQRynFQjgz":[-1151,-10071],"7wod1sFofmT9hM9XEjgPqq":[199,-12349],"m4RNtt3SmSvmvtXK9SksP3":[-7905,12151],"7trdKo2qux3UygMG9mM9d3":[-11215,719],"3iWFZ4DNaQaZ7mFmQuP2t8":[107,1647],"9QG9Nnph3Z9MUPH19wMd4R":[5529,2067],"shrpyHGrEAFpNEXCsnoY9J":[-9974,16492],"2ePdGqrnX7xeZkqxCUmHap":[-9761,12170],"gD6mLvJBbshsrNCdqMWiXU":[4139,11068],"kEMpNHGDxRMcq3Rwb1RGkJ":[15299,-5909],"4ENa7C5XS3MPDWk2YqoaUz":[-2599,12530],"7A7H6xg7RiGvha1qqnjCYL":[16304,1729],"bma5RSiuhdFM2SorStXZ9W":[-6758,7202],"4PQprwAzZuX7thecu73GBm":[-17408,4570],"rzuDbcm94b3zJio7qUmah3":[13946,4287],"vVBJxsKuJFUJWtw3oAxsC5":[-11555,8124],"gc4ad7Gq2uKTijX82x6QSa":[-11614,8498],"jrVjLzbiw9qo2r7pejwkXx":[3380,2211],"jmVi72d1k5R14jFzJzf7vp":[3098,5968],"dFecokixqRoCgt2Pq8d5yD":[-3745,10012],"qTRAQt6k2eDCBrNFcpchpe":[-761,-3461],"bWwWHkrsHroUVHYncvQqLZ":[-9115,14878],"9Mq17bbY5RXvcJ3ev7DQCp":[-9221,16165],"ugN5AwgFT7sSsUHF3yZ8zK":[-8619,16183],"fwQ7Juq12prPpgJzuHfodz":[-8919,16062],"ss8spjJL4QXSG3AxV5pzcz":[-8522,4516],"8YCN1Nbbsy13gaxSBhqi2U":[-10501,17091],"cfheXwu6TYFLR3U5E6uxgS":[-15727,-4],"4mqb63Kc8cBjwmeCcDLnja":[-5436,12642],"jH51bKU9oedbUMQqZ9MUkc":[-10766,16057],"1HUVDQq5fnHp5botJSPhfF":[-12108,14162],"2erBY1QaRfNQ6pHmb2CWAW":[-10957,16832],"6Fd8hRjBu65sJPts7ELgEx":[-10393,16396],"i2VdTuN9S5aRXJtBrbGMHo":[-10196,16610],"injJQjvDYJYfBzzwXqHgiD":[-11371,16171],"f2X1CqHCg3RTuKFGx7uT67":[-11459,16678],"iY44aahtbQUjo81j13nSVh":[-11906,15942],"hf9McB6MavEf1V4oiU3yLg":[-10045,11742],"twwBHeyX5ncDbSiJ8EHimA":[-2912,4681],"xxs4zgice4GSoGddXxCU9a":[-6576,-12155],"nLVJ6LvhbCJZmsz5LPkomj":[-8614,-10544],"po9htnXEQ3FrswuiyTifPH":[-2875,1849],"6xdHbdiYPQ3661i9XtjNg3":[11320,5413],"7vzckoczaYdyCSUkYn4ZiV":[1155,2160],"8q96yCquTbbZVQWXatCEeH":[-12283,5501],"g9Mc4iZxnWSL9abM1ZVEgj":[-11484,14623],"9zzw9o69zEGANnBEdXyaeD":[-10609,16793],"oJtsVmYHjm7bfKVMvaxdyS":[-10444,16286],"gofafZzWjotvMpJ6raLFc2":[-10323,13690],"cxcoZqbkwrzcYtnH5BXCJu":[5095,4109],"di3JeY2CAVKn4LYtK3ssxq":[-6538,9642],"ceuiet3i3kiHBHZQ6RvE4V":[-5018,5194],"jhLTemEnMbV2GHwcFT8w6a":[-4355,5817],"suoTjqPRpnMVjpZxRq8oD3":[8719,209],"c5xmNy1neFg4oM1Ngd2H1K":[738,3046],"smTGwe6W5ZctACSau7yuFQ":[-4656,-10389],"xtKRnthRbWXfRQZ8XL7tTw":[4719,4023],"sMwUFeQBaGr4A9vKBBhJTL":[-11067,15825],"3m98FEPytyL4V4aXUcRRV5":[7109,2681],"k3YvxeBcPrswzybQGCQdt3":[458,5759],"xi6Qc7E6BXHS9X82qi8Whe":[-7031,12068],"6pPpc8tCKkXRrYRNiraums":[5444,4121],"pHM25qSw2926YVGkKm6bV7":[-10940,14621],"n8u7XuEkpanuoRskCxUpZU":[-313,11598],"3C2dFsoh3qWc5EYW4guX91":[-7309,3932],"r9yW5hSL71aeUQCF99C5Yv":[1788,-7529],"6SuKmdY7sALcgv6nYPB252":[5306,4533],"mGDPR5zgesnptRnVaL8bBN":[-11100,15654],"fYcx1MmBgjZTxKMQM6touC":[-9899,17144],"mQBRM9GPep3FnshocSDias":[-10518,16500],"5WfY2v84s6gRQkuUFpTqBg":[7720,3190],"tkU3rXahpzmrTMzDJGVyZM":[9476,482],"aCUAATcJxLVQtRxHvdhXG9":[-11261,14959],"mN1Xw15AHf2W2myDnJP9KE":[1442,-4709],"pF1dNRoo3kaDwYPTDtVGQt":[-5651,-15438],"s2d8h3VqWj1DJs3WT7ZdRM":[17400,-583],"hrhgHZaaWDDNbDyv31cPoH":[77,8238],"3Qhr5EQdgUNZ6yGNxCdhyE":[11288,-6643],"nJs9RbHe6VvqEzumnp34ju":[11689,2854],"2K2fXiwbg95kUuMuNz2zFB":[10586,-1541],"of6g6FDMdXUtWJGsZgLiid":[-10721,15600],"3wNNTFL8UxV7hNH5J9Wb2s":[-12752,3057],"qNDMUtYnphCmLkBSgcsyut":[-11852,4941],"k8V4MJnrA9YvPcR6Ef4TCw":[-15845,3794],"joBnD26JeR9CU3znb5fubm":[864,2931],"nziUNdWyy4YveAme9WiaNW":[-1656,5998],"ccPmhEMqFrHzv6e2iKfDEF":[-9138,10207],"qtqhMVSEMpZyhYhJayG7Ca":[3958,1304],"6wprgFqf3cTTsBY93aEJEW":[-5033,13047],"vbQsio4DApZ9niqemuW2gz":[-8342,-11191],"pjk7JvsXf7JYDJVctx8rqE":[-12813,-2192],"q7RZ5gZ1ktsrjdecAjEaVp":[7703,12096],"wHxd932BzHbRctJ2NtzKC5":[-11983,5493],"wAvFBGxApq4Z2u4u9AnD4X":[-17556,4070],"pnbAhbNYS2mi9v9fwtPpHS":[-16925,3494],"8gRr1YZKWhXt2TyuJsmMY5":[-15162,2876],"aLPUECuvtxWZcCKvXnetco":[-13429,2187],"bkDvFa47wcdT4qAGUmN7rY":[-13063,-2528],"wYFXiSu4j8YgJtcYkq5vzH":[-9817,-2627],"iQGLq4QFdbw4vGx1sRCrmz":[-8935,-3059],"qPXCe1uMnbMNT2XT5VnpyL":[-14685,-2074],"v8cha3NGfyzku5HYnfbCis":[-10063,10477],"gCYqo64Wu4ezgLLLTARhNZ":[-17156,2998],"mVL6BN72Y8WynaEoM3cnw3":[1337,3721],"ez2wkVzUobQCdExg3Ux3qn":[11126,-3715],"8kGpBtKy1dQXrPjZRtrDE9":[-5525,-3550],"4C3nxbDE9PY9dGffL584tg":[-12472,1532],"iRECckPDERMwE2BijDPNmj":[10783,-1750],"xw9BmHktva75GFMkQjdYTW":[-3170,2337],"tRL5RGfYtHU6VfYYWBoRUW":[11583,-7276],"gpgKE4xnbaiTtiLfmSViVt":[-4058,-10859],"fAq8P1GEdCgmxoWgAYKL9F":[-1046,8757],"fuEbasMzcwNv8breNxiSmu":[-4863,298],"2fxxVdChLydipmieEXAHiE":[1454,4359],"7fpY2KCitQRuUj8t1L7FQS":[903,10214],"1eq63auuMkADMXLRcRokKK":[13281,-6302],"3Wg4n9xZD51Ufto6zXYjgF":[12669,6135],"g4qP7AKGHmNoLkfQcvxybs":[121,4848],"cxTJVVNbwvLfPQjpeLpe6i":[3093,914],"8ZuJKvtKU7FjVoRnXJHihb":[-3279,5271],"qL7ExhSKcg8yQWAJEu2yQk":[3273,10246],"rncmoLAX9FWguwLtqxpGmX":[-5353,-14828],"qcpJ63cJ597MwHdpphCy92":[15087,-6268],"f7U9qN9uR4B9KjGdVhCcZb":[-2853,-4205],"iwcjrtuu6f5H3ZoTRcuZAQ":[-13001,-3152],"kGffC6mUUvAgxpy738YbSw":[-7839,-11517],"tUNTtHd3uSAMtixPJGVdDw":[8692,-3434],"ejMdWMp14D2dKYoSvf3zjp":[11744,-5148],"2AnNLjGJU848chXwuQXemJ":[-5394,3178],"oBkmZ7cSZVTbs1yYyhyCXt":[-1491,6829],"8P5h2M2ZDKNL53AaRQ1qW8":[-7575,-595],"1i578Sxs1jr355ZSAmMZpE":[14493,-4172],"4rVEFEejhZGrw8nvWsEScG":[10626,-5988],"hVjHxTPzkwGxZg2fis3cRS":[104,-12163],"cbNeEbPws8r85zNW5JMW2Z":[-8133,-15188],"8DQzvhkDmy7DwjqvRUwUKg":[-6908,-16254],"kPXCkNirDGsZjYUd3GsJnE":[-4330,-13173],"p2RRzp3ieXRmwwqMphyBzB":[-124,5641],"mPKEAfiFw2AAk7WzKVrGtn":[-7263,-17100],"m4sZyuKF8qEJfsci5k6mrD":[-10033,1447],"ruo3mxHg1HEL3e7y6bMgK8":[-2551,-4111],"pg5V8HUzrtHN4Jz3cLf9rJ":[8099,1566],"vG3nUyAkaQATqKV57mg5i5":[-7651,-14068],"qCzwJAej1Be9u52Hy9d1sZ":[13091,1515],"piP1yMWceYZkp3sN8jLqg6":[-6859,-16078],"wJuJjYeLXAYGya3cDum2uL":[-4849,-259],"cvoJYete5DgsmDPq5Wn5rr":[-6650,-9854],"pf38eFneNYsiUqLG8CdqJy":[14087,4996],"65pymmgA7QMtkHXbRjZbFu":[-6649,-11594],"bCbLRZjpRKx1FTxknSCuTQ":[2095,11881],"3ngmRUHNmZTdMDFfPVcD5H":[-9403,1634],"jJxe1Bw4sWkKQBHBp6q4k5":[10489,3352],"fbn768mFfNmcMVj9Yip3mQ":[-11243,-34],"a2dQewtnUCReDEH5zuYLMb":[982,10903],"uJTwvkAH338rMH8DrX3RDS":[-6907,-15379],"bhTFBXNWpGJGoUEzYBoihG":[14202,427],"fFpJPLdeCS6K1UGAvKyJmX":[13628,3018],"1MoScqrcGR4WtFkpZT1ymv":[-1982,6468],"t4JUj8WRGPZjcaVk2HMUef":[-2107,2252],"wzcV3u4rDknA2om3ZWQmj1":[-7769,10621],"9H4iAK1RGazpGNDMQdEgcd":[-5991,15096],"nz4zSu1hLMypQzRJo2xPca":[-15820,2579],"8Y2hLefLb6G2AjXXFoRnZK":[-15271,5670],"w5wfJBazJU2zUU27WKbVE7":[3436,1304],"fyDkJYJTgoWtvx1PqcQ5Jb":[-3930,-9236],"dm1YyCkts1boDRohLHPYkF":[-14523,1850],"6rXGY38W3h2R2zYRXppAVr":[-11583,2945],"hNiQow7jcYoZmkar4yM2rs":[14277,880],"rrYt1LRkfCpQqPwnQu3h1i":[-1814,-3313],"q4jJSYitD3XhDigiRRDVgP":[4643,1685],"uDkt45H5s9CW3gCoM57jAz":[-14419,-1367],"o8WJWPHivKFMMPF8MnhKoY":[14104,-6644],"io1J11TDgygw1C4aoJx9EL":[-9624,10662],"cbNWvfnHDWDiGx7VxfoCKU":[-402,7188],"x2JJQ1MvEtqbfZw5LAsdbR":[-2070,5419],"3c59EGavVNKntK7bW5LR6o":[13598,-7438],"qjWfX9Dg2PDgCXaBHRqiBB":[8627,2667],"fw5a6P2uJHHwag2vp99nmp":[13463,-4042],"7NdN2SdCARxtsaLhVRdUob":[3556,9332],"seeb4RDnuq4AX3Lgd7gWwA":[-10523,-7433],"r1ntspTwCrRPyQxbaRJhCz":[7751,-6061],"5LgKamPgCMERKnbUw1wzbt":[7334,-6506],"h4Bpwwbqf3sFncfu4vMpK5":[-10262,-5329],"jsBWdwHLKqqBaG2xpcpNbh":[7588,6914],"t3P6qn1aBmGKgdA7CH6MUY":[8074,4242],"vziu4acEis228AujWDvsud":[-10622,14370],"qp5tLZZqqZ2r5PB59vjmw2":[-11674,15832],"8VgjnNK1jYRpZbHU1jAMtE":[-11272,13927],"xn2J2VW4RgNqjzAiuvXoid":[-10759,14516],"nd3z3g3AJwWueDKAGFKVZW":[1784,11163],"utxnnJrNjNj7A6AAKFVwzH":[-11417,2618],"ny15kGZuBXVhUaFt6QRU3N":[-6227,14504],"9MePMZrMaBvykrUA2WQM16":[4927,3724],"xaZbg3w8cNQVHyTx37ePUf":[-11011,14399],"1rH5LwQASFu8NxB9qSHGt2":[-6567,12574],"udQaw4s4V6MUFzPbXxAPQk":[519,14727],"jxJvHLc6y4uZry6Yiq8J2Y":[11364,3578],"rdrVvwPbS8RCNzMLp1kzNZ":[-10222,16733],"ox2tXRL2ZUQmu1S2Y4QYPu":[124,8953],"eAvRkxQBxUDHRWFHXgsET3":[13867,4788],"iP2tDjk31RkeqPSzAmvwnR":[-10770,11412],"mhSiqyxwBq1o1FDyRosV8z":[-13318,1383],"eCBbzZgnkYf1hAnBPEwaQz":[-6983,-16464],"tQK3HcxoJ3LoZ6imUons4i":[-16852,3019],"4JRUXPGCnngtavDFBXRHNh":[15045,-281],"m7DF6oQEQQQYC4pyYWSeTy":[10510,7031],"7k2bMXtfgGbQDnf6jiWCCj":[-9131,-7946],"weDFRjUaaLiJq9ThZBFXCR":[10119,-2842],"nmQBnmWNQjQ9ag2rDjPfGk":[-7381,-16220],"4qcbvVKs9EZ9CE9EnYEJd7":[-7179,-16777],"axPna5LnDLsKyfr35mkZms":[-16102,-115],"1bZX2RYUtT4LEJv5p6Ujij":[15843,-615],"pDrM8rAzpbnaDZwvWnoFof":[-9492,9782],"tatJHHax2DoarcJugKzwgU":[12609,1932],"j8dwB5kZ7qXw2AtR5oNipt":[11044,3864],"dQfZXMj2wuxRLYyrGqUL2H":[-11271,8000],"tUSnrBnNZheTTJ76yJWG6R":[4882,2729],"qLGsfrjwq2qwXm9MNbZpon":[-2672,5496],"oJ5WsLPizPBVRK7ij2z7Fi":[10010,585],"t5vWb7tZ8wrn8QXJZJ9Lxy":[8181,-2272],"dNhT4Eb1GHuiTu7B8JLVQn":[11151,-7285],"uKKzvu8ZWNp8JWmaoVcmnu":[1921,-9030],"i5t86bVTU6ANsiRgNuxiZA":[-13109,-7243],"fhGQXsNiCYUBfwmMeKGAhk":[11330,-6515],"cccr6uUVULt9TKrDs9VpgM":[11874,789],"4FrkZA47ioJaudsR5pRcPM":[7425,5315],"k3G41747QKoCPL7YrvfJXZ":[13101,-3193],"jwQt2rRF9vZTcm4gEdciTJ":[1010,1970],"sKtHWB9FXNvBvjmmmE13ya":[-12690,-6833],"hDrcdrhsARGaGfvDCGey8v":[-15807,4865],"ad1Xu1YHcA9KQHvcZ7Xt7c":[4522,14371],"71DYSkLVjUxhna5zvSHRsB":[3075,11000],"tB7igaQgCYDyxJfJuG3KQ6":[-1352,8561],"9AEfztST2upeg1mSgJAxhM":[-13712,2662],"vRZSoBVM8yckQRjVvQpwqH":[-264,2473],"xd7d7yQiGZ2r2cGbSfu1Y4":[5423,546],"u74TkqZN7Ju7PXfTXBAKtb":[6507,-6559],"c9wqqhiZeHTSuF8QnD7zcS":[11765,2097],"1wXhu1A6JMA7Z4HwjBDZna":[-12907,-7629],"n2fqbYUmcjAzuJoBtfFX62":[16814,-1125],"kHnGkVkvk4rvDbmvL3M8pM":[940,10443],"4r33MLZ83L3MuyfhLQ6afo":[-6152,-10940],"rgqqrWyPzTncBBPjaXsaS5":[-12078,2737],"pNvWSZbeBpbQp84WV2mMUg":[5506,9911],"eU4hP6ELCQKcvzvECpqnJY":[-3846,7068],"7uFAApu2N6Xex6c8oFwBWm":[-185,11726],"nhWpX1KSDaeevH1pT5Tb2U":[-1943,8694],"doE1VAptodkoUcffeEWkBa":[1310,1875],"k5srkjnb7RhB69Vgv9Vc7v":[12859,-757],"rdniHqyacr2keG1giuaZmq":[-10921,16942],"92A61pg7be9LtyGmfSoGBF":[-8757,414],"e3sn3Jftn2Y7YRFF7kUhY9":[9287,120],"e6qyiNZPz9b8hAFMjCf2hQ":[881,9703],"8YHMG67JcaM2Fz7GXu4QUg":[-3704,14669],"1jU3Zk4fT79vRPDTETSYxt":[751,7377],"tXLUUuuNXqxE9nTnYvFYrV":[1466,12242],"2rxR1rUHD9eE9YtF3SCx6X":[586,12219],"xcZeoorvxDd4hcVN7D53Zx":[-1240,11211],"c3TTZJdV6obVQBNc1JzhtA":[7594,5923],"qNVLm9wHPs5FJBsgrDFGt3":[-11305,3158],"fWqGDLFq14Kq2bBBg8QAN2":[-6713,-11391],"vNQ5rdWVmP92DcMRR1WE3N":[-3097,7540],"wMoDNRwzKXiU3s1ToF7qjW":[-3251,7237],"5EFJE2u13ERLHSrgQhqu4j":[13810,-1779],"2m58vbVatvw6NP6FE2ErRp":[881,11953],"7tvTfW21tZEVig7gupuMrL":[2447,507],"po6a7ikf66J7rakqR6kkbD":[-3262,1923],"rm5nK6SEZZV7nhFEiYeKUf":[-4109,6124],"6iHTCffj8gXR62HGH1mJuG":[6266,9553],"7iu8ASJ3KkgLsN2nqczxnL":[3078,15282],"cAovxs5NqERGsCF3CAxJ5D":[-243,2114],"iATdEGY8d7rD7r8KfZyhx2":[2828,6453],"2poD4KQ7BYLAvPNvbTxyTP":[5512,9182],"mSsUCChDtckHgyc2H1M5VP":[4214,-2657],"aqVKv6rQ7Fo2gGyRbP6VAY":[-1030,-1731],"hS6vKiYDirnkoYit7RuraE":[3951,15122],"uufZo2rTqpN9uLv9hMwpkv":[11377,2865],"hbb6CMZ1PALH3jgBcYHm7T":[-10158,11001],"5BsjDiUME8iCGzaRy4Hm8D":[-8371,-4620],"qRWcPgq8EhxZ4vasyjQ11t":[-11522,13737],"qHte3KhpjKjRf2X81BZNmU":[7020,8180],"9kd1TSFPhz9y1fWm71kpSK":[4062,14826],"v3HYCMv39qoujSKZovHY6k":[14278,4453],"xdxVEZ9Z9RJDS8VrPDDkyN":[7451,11243],"rTTG1zkjrUVgF1pSWoYb1N":[6477,8981],"wHRG6LkGUdPWVMQBhBLR6z":[1300,8618],"o4GhHJ1d78GbT28fs5RqZp":[4481,1352],"chYzaetCW872VqY3Ga1JY7":[-8243,12032],"wDWPYAXiLZ7qSr2xMixe3P":[-5838,-15171],"sigvbS5pLbEyVYK8mzRed4":[7655,11490],"mdGihTMUCHbpyeRHULTsSZ":[7260,11083],"pSem3VMxm6P6aj8gJ3BzM1":[-7150,-11204],"gSTbc6H6TyMhZmxutQ4MRL":[1930,14343],"h9vtTYfRPKgxCSoSgicBTQ":[1287,10227],"bfyHR98TLNcozaedyAVAkV":[4239,11409],"6ZxNAfcgTDGNLwGbtk9dJ5":[13206,662],"19WsG5Dqd6AW4ReojKR5bx":[736,15130],"3v86Lg8eDCfFdpZKCUyEfK":[4586,-6235],"n7TAyTjrF4Dfdm4keVraMn":[-6079,12568],"bHBcgj1DqQR24dbsLj5BBa":[13362,5268],"dmpwZuWPnxQGwogjJQqEYL":[2648,-7093],"uFqfhk1fMTYRoAj3P8ki2G":[-5994,-10812],"68J7rEF7qSTTC9jAZhXE28":[7712,-4865],"r7kCSB8kBfvKN6wt4nEfdW":[2718,8704],"8hdiEFv9xahRWLi6HCc3XR":[4909,9970],"gwmegFExc7Lz8Ympg2pLUH":[-4892,7881],"r1y5YnTSek97u4AEDicf95":[4822,9621],"iwC1Ayd1gB1Vr91HYnf46m":[2349,7908],"3pPLDQ1VmXmrZidthRy18M":[2355,8563],"sAmKVMqJnFZgw3oGXy91wd":[-10879,2459],"nRLFe3QgvPxmmmzDhumUZU":[4337,9930],"qp2HVxmahNymCTevqkZ91P":[4621,10183],"mVsiaTZkC26QS7njdpyauU":[-7442,-16000],"k57Fve7MmxctdPj5NSFmEa":[-10314,16861],"a11mxtJ4GhLeD67nAGcpUu":[16015,2173],"5Uf5xFXt55Fouho5X1ccQ2":[61,11853],"t6ZxVevWJH2VaUfhNLKkwP":[-4587,-4668],"dV3saYHCmgV1QKei15foKj":[4404,11541],"4uGRZrdjHKvU9BC1FUG8Xh":[6611,10614],"pJuQ3MU6k2xWLNwEpAMSP3":[1277,11238],"heYAQqhjF3zXnhQa7dYABp":[3735,8300],"82MvckiJm5izi4rcjC5PoA":[-6129,12770],"fefN11n2dxcBncJzLXwJsp":[2197,10052],"9vX2b4B3ydY5nzi35oQze3":[2434,9791],"c4aoAJgANRdgdmYKRoKnYf":[-7896,-16433],"oKVFcaq4nb5DSTAsV5MTwW":[-4940,-14750],"h8Xq7k7GBGDW23txHK95Pu":[6346,-3528],"9zkkBMGTjwn9XX3wivoVD8":[-3217,4062],"7e55zsfoHpi3ACfhEx7sdM":[7886,10805],"cqesqA1g6EHu8vrBxwLqxe":[-9005,15644],"sYzgc9KA4YuGfX74FiPS3G":[-5622,9826],"pRzGXVyBBayeyZ88h3eADr":[-9947,-601],"5D4BHdweWGoQErxaa5uA4o":[4091,-1426],"cFqgUM1sEeKvh8bxeuggcg":[-10412,14733],"sysrenmDGBMfKmhuStvpKS":[2566,9323],"4rjrYwBQBURNzCrNXWYGdF":[1831,9178],"iZQ6Hg7YKSCE2GQMg3jzDB":[2132,10441],"2kbE5gXYMS3Lqx3aHDb25D":[-11050,7313],"sWVam4AHwLv1KxVzjniJaD":[2143,9940],"vF2qkvk8HBzXWY2chuWTMc":[1683,8315],"q2ciWjb5p1iKmooU9Wypwx":[1864,5122],"aeQpkrU7Zaeh3m9PX2k5h1":[-3161,7748],"ssNUnncaNmQgK9z7HVf4LY":[3249,5331],"rtLk2aG58QRLhNuWpBsExY":[10525,8422],"wdnSyDWJKEykSnFvtBBa6S":[3258,8946],"9Tuqz5AsYroApPVeDMVpJj":[3558,1769],"i7Q3naPENPwrXtu4jUEKFn":[-6025,12431],"kT3dcS35avu6tQtmsdMhoV":[-6091,12924],"4EFVgYdLaedgkJwX8CirXr":[4794,-1687],"iygMqcFvjM4qtzxBrfkJH7":[-9624,13680],"sMMv1NjqPm4EjGPv524hSS":[14203,-1427],"sVVifTWPUtFcnsxNcCMoSE":[2794,10254],"61Sp4WZv63Co9CFg8FhAHP":[-7452,-14208],"eQYzrpvc3A2BxdnZNZvoe7":[-10314,15252],"7YVs4kPdUiDy93ySePGmZz":[-2226,12818],"xyeoagRbKH19wFqgVWDTkC":[10176,4554],"8kHUco6EzZtho5PWJc1Eci":[7435,-4031],"5bFKReuqmBdjXTrUdFCPbX":[1131,-116],"cG7SwyHAFrSZP6tx8wPocS":[-5053,14569],"dkbQ6tTMUXJWoxf1dJSZjZ":[5851,9912],"6dSSZVnGjB6Qn13v4nq12Y":[9218,6145],"emD9EdHuwbYzAB7FHnNSdC":[-2186,16463],"s8XKCgtbuS3Bu71yLMxdaw":[-3769,6520],"d9zU1GjRHFQReDGHypMNJo":[3102,-3771],"ag8JFCLKFgMzkXKQrhb5Tu":[7759,166],"7hb7jfCaFW7b4APybWVDve":[-2732,13139],"v2MpJA3rC2W3gmDvaAFK9r":[-2097,11046],"f7eKvkUrESDD7zYDpbgVC1":[12367,6116],"tv6YatzokQa3orWkbZazbN":[-10319,14458],"e2AC6SR9yAafVVKyqdaAh8":[-12604,3248],"oruPEc5275prA6g1CcqTuE":[-9958,13563],"ie3t5gnp124ttxqk2ZHvY9":[244,1832],"2YDMbCQVnYnj1G7krMmt57":[10191,3586],"ix638PzgqrWTEyNyc1PeLG":[-1417,4453],"2G8fsizKsWwtFdSns6suMs":[-11114,13177],"nLCebgZQzsma3f76fAHzWr":[3568,10368],"8TEDu9TLiEqX4zmNvPXRLd":[4449,7965],"tc5PyYspDgZTVQ9DyFrWK7":[-6780,4759],"qiuSz3EZnVurKKJzbiDt7S":[-6789,-12976],"kn8n37EPYgXmRBhssVboEe":[-5197,-15147],"vHABPZz3vgLYz3DpUWcRqa":[-2859,15444],"fkCTHcn5drU6FS8PthdyLu":[2492,-10900],"pNVChFYfyRUDd7W1G3yVdE":[-11197,14160],"hfdoKSe7Ci2ZN6T4VucNvv":[-10905,16727],"mNfLF2JppLoRnYDAjEY32U":[-5305,-8823],"vLaWWL9H64itrdEHCUEj4k":[1602,1231],"m18AYYTRgjNf7xGz9NeijP":[-952,7826],"xp3ZcujVLzd6TbgwQRrgRV":[5707,10669],"t8pVugaWufBThSw7uTQxSG":[8412,5923],"63gVHgBtNcfVWdr16dMFRs":[5206,10129],"h4sUn278ipqytKpDTGAMLB":[-7312,-15154],"mYMa9hTxt8qr4ErtHXLpej":[1040,3520],"xtwuf8HZdDYtsong51KiWh":[2200,1189],"wwxeiRTz8YSeKpoLrW6xe3":[-11009,2972],"s1sujXq3HigVQb3aBA25TX":[7481,4272],"sc4JGX1fbPPpUMYSPKTjKG":[-8469,-10878],"2rXfsd3yHsVhugf7UKXQxm":[-6025,2565],"aKmcj4t2PeRnRATxV9UE41":[-10812,-7091],"xagQJQLyVRy9wukcTLokh5":[-13535,3244],"mmASurNKjAwKgVAePMhWo4":[-12454,-2299],"9MwvqXvMGnWzqMn2Kxktni":[-12227,4593],"73HzcsyvqZAcoyzxZjpr5P":[3821,2537],"wYLjDNgoud2gkJKZWycS9e":[5284,5856],"ftQrz2CGuCb16g861SC8RB":[-11005,3092],"tdngD3bay9r4SfWyLrG5Pk":[-4708,1396],"jDGRLRVSuPGtNs1a2SxpxT":[-135,15094],"akcB4Ut5XTwsTuFHedKAGm":[-6197,4330],"wssneX8PG5Wsff7Ya1mPkj":[3139,7910],"cK6g3AnaAte7h39EeTmF5V":[-17343,2631],"wjhanCGf8pnU1YFstxXipQ":[2219,10167],"riwN4hT31ZiL6qNR1V3RtY":[-9525,11152],"fY4t8zgRe6xFUWjVMfmaYs":[-173,8838],"oCyn5q37zH8Bu2LfDY5vdq":[-3145,1319],"4qVNtBu5zSfnTVeHgvt1b8":[-3007,1696],"uvp85mxgmAcXVkpW5JhFGW":[-3556,-595],"nkLdviR2GE1iuLspmZJqDD":[-2606,14327],"wWNHwTXQaFLS7iepQXtTYp":[-13823,-5068],"7H76h5ksMzLLN2jQyy7kir":[-3350,8279],"rHQai4kbfWfBcqTCpRaEBi":[-6995,-7211],"wxDHS3zkv9SHmpaKJyNi2M":[-11979,-1133],"fnA1yPndeRZSRLXFTZtCKb":[-8630,7152],"gDtAbzwDDauAPMxjpnYsNa":[-3883,-1006],"rMj5njCkrLgtjedwGto393":[-11243,-8237],"mb7ssyLttrKdaupHJdcQns":[-4273,13931],"3XHeDibWYV75yiBMcxZewX":[636,1765],"2Lw1KzZKAkL8tLRdbwBAxV":[157,16699],"24K1uwHqyJ7TYCmYHGbN9e":[-14646,4586],"aUJALV8xgYnjjtCwegZj7i":[5615,-9498],"m1AVZ6yqVHRKE3dsLcsGe2":[3132,1312],"hsA8aqu6wVnnDdiSP6fruM":[-7906,7428],"fM5Wzajf8b14ED22cqj58D":[-13142,1842],"mAE9dUqe2PpDqP3Ghdr91k":[-6702,4895],"iikQMTJiZSpTs9kHu1nhcq":[-9550,6073],"cvJPBwxU4EkpkyVc1KoVMg":[-16337,1996],"vqcYYkrkrR87NjjGReS1cC":[-6287,910],"of8Uyse3xTd7JMRkNYkCPY":[6266,6072],"511ZkRyk6wpyaptz6W5gJJ":[-10878,15492],"tJeXza69GdLc7cNYsCpcra":[-10695,15732],"w2r6DUL5npqcjHTneBmULE":[1178,6439],"w4myh5pZnXxmqYfyEhuiUA":[-2487,12170],"x3McsL1G7qC8wmyaNotbP6":[-10136,15812],"1Y7pMcr68c84rWmKNxpqWR":[1591,6585],"rJj2JtG1m52EjmecuBjiaC":[290,16540],"ttcPq7zanAG8YQnPMyCA2L":[-2367,-7380],"mvYS5HNTRQAsUt2vk99KUH":[-7073,14619],"6VxJrK4ErJwyQEbkDwwpxV":[14182,4057],"6RFwga2i77XCa3bxUTVDvP":[-3364,282],"nTbZqa16bK6CY2jfSLAwBf":[-11069,16152],"c4a8eeRaAMwKDpFRDyySeM":[-13102,-3388],"avL33YcavETkFzoubVmQNR":[-17045,4182],"7CanqYVNix8boJ2nZjDdX7":[-11855,-4141],"sCYVNUqgHmv2mkkha2G6wJ":[3437,8379],"kPv7YetD7WvBmtBShMXDro":[3044,10828],"4AmZmeL9WUrgxSvexguMp5":[-5489,6958],"xA25d1cbfU1gjniHiDFsaq":[-1322,3401],"hxUCZFPxsEDz6445yBi3do":[-12676,4797],"2GpzY53i693sj3QwMgZv1w":[-14227,2913],"gKmVHvFLbpSKLs26eNWEbR":[-17392,3681],"vKibtE5C3GPPAWSzseridV":[-6643,14946],"9woXmxL7aBZqjWhr9VBUSb":[-7990,-6547],"6gGbHn7wGjaJiVLBf981iR":[-9750,6431],"e3QHJdxXP1skGv9ASwv4G1":[3853,1821],"dLMREAv5fs7sCacchpnjRT":[-9357,11557],"dGgeH6zSHem3EXTjMNXKWG":[5240,-543],"f5EKrNeoF7GyG8Ewq3fVjc":[6362,2165],"2FuBVDmHLPNrWCngJRy7ey":[4324,1804],"omPeiqqYzc6GcYnBa5s575":[279,9761],"1iTFXZviM3kThuvBdGjxb6":[-2808,11482],"iEEbu2kRP8XnHPMmMcC2Eb":[1943,9493],"8BgmiCsbzf3PRGNkVs2fpD":[-8210,7487],"8ZVXtTdZcLatn1aUH5PZ97":[-6097,-12788],"joHwu8Y9Apmv1NmT7Vo1Hu":[438,15624],"3nSs57LcaWyo24iVjUM88L":[-3859,-7969],"qyXB6zBGnrLSjVV3G5WxCS":[-7278,-12730],"turUAo4zmzQG3L3RQYpubW":[-17557,3869],"4pYehob21EFRu3Q6bDdQTC":[187,6895],"p213n2VWj2asuhcEZjNTtj":[1766,12148],"a8tGDatGyaCk8ihPT2Z72X":[-6068,13516],"xefk2VCbfE6ZuzbzDWis2e":[-15872,3028],"sSEWAUa9czBNmfBcHZcp95":[12365,262],"tFkmYuqXVdcpKaJG4YkFW6":[6379,5401],"uf43u3LAJaME7F7BbSEPkM":[-1500,10389],"8cbqSLBhVEMu6fLY9qfGoL":[-1498,10614],"rqnoC6ZNRGVHMR3fjZYRya":[-4330,9229],"i3ZexQcLhinxpExyknM5bB":[-9675,-2511],"pnSKZqfweVQVP8XmipsA54":[489,3527],"9yoivhPDKrpbJkSacZ1ufg":[-5231,-550],"fjiJH1Q5om3fW9sDBCbuoz":[-11165,2093],"oTRav1ch7HnbZxrMzYHFTE":[-13138,-5127],"uDKvp33x2mMVCogAi8njix":[11116,486],"7T4ozyBsfvAQFishDdMPXT":[17557,-1262],"dNj33fgCLHYqrgaGdoKPRZ":[11709,7583],"sV9JixUyHcmfZJwarX8PmT":[12046,4775],"kT6afdHnu4BRP4tg4f5Cvx":[-8726,-13498],"cdEgvq88diwmKk9g7YRzWF":[-17868,4446],"8iJexXgBFcT4GnstGXgnmt":[-11930,15266],"czws97xf9MJM8TC93JyMyM":[4937,5062],"kmMPewnFYMcXCDvh9xQwur":[-11579,14171],"exGDr8JQpigTaQAvQKnipc":[-10031,14792],"tVrDmotE6vrQSVvsNjEfag":[-10488,-3103],"rhUMFBDSi2DBbsiV439vH3":[5452,1636],"6uPqGvQSKghF1CwoVYnirU":[8622,3949],"mZfTzJiJXgw8XXHCRBvxeu":[4639,5030],"hNhJh9v6n1VGmsTpdcpfb5":[3308,9448],"iJ9YSBr11KTdgAaY3wCkkx":[-2310,860],"4T6p8QQa4H1f9Znp3eKsW3":[2947,5374],"qDdThK1iRVdFjzeRiFcmp1":[-6804,-13092],"5ozrZ6PcbYzhQdZhL2ZhRr":[-17563,3971],"wceGs26B1Exw2dckYhR4tG":[-5419,6556],"6HLPpdAHmG9tbw1tx1hZxn":[-10747,7404],"izUUB3A8PrA4kPgNYm3zvr":[6120,7940],"xbpLfxCTR4uubnsRk976Jo":[3021,9183],"huRRu8XpjPC1pY3UuNLjxj":[-12888,-6447],"9S2qfUtoKn7FQQ5wBqx2Pp":[-13192,-6347],"tKFCg4bcd4WmkUeBaT9HYx":[3715,-131],"aWMtFYAXc5hTrTTCjpVYAy":[-11154,14035],"bDhfy8SxKcD5MNo44mSGhf":[639,10433],"t5FBjDoD6cEFrRh6QwZY6k":[-1144,10813],"wokJV8WSGPEAPmbTxijmmY":[12065,1758],"fCvEkDyqoKumeufNgpTJJx":[-16216,3011],"1KKGcVCH7zemNTahx8eXQh":[-16612,2700],"7suRw6Y1Wm8FfBW6sa37aH":[14759,-1364],"x4sUfCrBFs362QnnVNqkoD":[3083,6097],"syguczMG3uEyxgcVmRmTtP":[-17498,4768],"hsKh1M9SGcizcXqP9cdUW2":[-5151,6301],"hXhURFR6ZDMbNFK3M3XXEP":[-3180,2562],"xuaoowLdRaReqEBjcJAQLM":[-2907,2186],"wYCCX4bDrosmAfBdj7Eomk":[1799,13437],"kjEPkaPqAgumdPfTGsiFYR":[96,11969],"dn7nAvoAsVJcoGp9z4cf67":[-11175,14281],"p8MHwi4hFmaLPPWWVn6LeC":[-841,10908],"dq5P4R2VoVD2154vrgq7HW":[2943,-7958],"9QPer2EqrcJJYpKX2CJ4np":[835,14301],"aGfhUvKFLHxUBnKEW8Q4xM":[-5186,7037],"8nk5yiuBwBT8TUY6wbSEmm":[3519,7592],"ncv3kSqRsEU98Kc3xmp6mC":[-1494,9546],"9YahCRoxkCpifhjZngfmWe":[1734,7272],"f3xiZyzEf9PhJynwS6ndtn":[807,7145],"r3jM9jgkt1KNLfEtiWqfge":[-252,16627],"xfr1aVqvz9VBh6e5Nre29j":[10289,6243],"kNkQ7AqNbhwqqK6dpgsaqn":[-2749,9129],"xuJpEDtxjvXyKL3HRJdn81":[-5693,3807],"sVWSeEGxMCCi49HX3G6x8g":[-7778,7772],"fgpP2dPwSmEyvoaTtpeZ9Z":[-3589,12021],"vumBEpPoGNXFXE9NPMr2m7":[-3040,13147],"jazVCPiBxtNyBxzqwt1pth":[-10998,3213],"rLwvavtaVsiPWjccL2qkzu":[8740,-1735],"vSkMYtXWtgfPHeA3YS1RRy":[-9190,8172],"9oHmiHKm9jQJ8p5uHZWx1P":[-1879,4696],"3r9K9wUgmT5mtr3Jj9yno8":[-4737,6527],"bUuS7mrVsuASZiGdy2M53w":[12043,-3558],"cwS2nur6sbhc1PzHHqWoEo":[2494,1077],"jJdP6ZB2Zws2QmwGCSyy24":[669,14558],"sHMH2FtoJCeubDEnreKEAY":[-4665,9647],"hjKZ7NT1LnEU7exFYKUMUk":[9826,6949],"9EfMGv3zEWC4U5rgysoqbV":[-15377,2759],"hgg6tcNDD5rLEpQwyBGj3h":[9414,5964],"eTGxQBtE2ZaYuwUPumgke2":[9792,6021],"gLWYaC9XeWyunnoA9w5T9L":[9470,5366],"mtbBzRnZipeXVh8MdbbTqc":[-10508,-7174],"1ACHRDGnGTu8uixC4244jz":[2308,14875],"kSAQwsYXC681CEreTZcTce":[10508,3490],"c9Ko2MWmK6gR9Cz1LkdajV":[4037,8449],"68WN1T2j5tWSEHaCp9vuRK":[9690,6668],"6dD17BHyV4tznwgJTaknGm":[9526,5228],"jN9XDejcFpXhD6F92S9Jnj":[2056,6094],"64hBn9xEZqQEBGutnPn2vF":[2006,6585],"nbCCnxH1EB6X5nozZSkK4t":[10485,3939],"5HcKyiDfMQCCNXsurMzF6B":[3738,8793],"gcAuqSkrHNxsRCE5e5Mbsy":[-13358,2303],"5DYia1wTpRtJZ43cK94JNT":[-5674,1140],"4rDmSmYGbERvMSi9HzkjcH":[436,-11906],"we2GkfCfqPtFSTMNaNXZ6R":[13635,3720],"xfwB8apfG6LmLwe46QjKAC":[7377,7430],"kZCimmgSpWScTy51rebxkH":[12395,5119],"sgAQ91bjiAVoo1kMJQJdUB":[515,11320],"sPCo3pnWfZAU9cmdE9TWn5":[1564,5085],"q89REUySHKTYhHBGsFDZRP":[8205,4683],"oFudTw43a7BsDQKhcKSd9Q":[11762,3924],"upxv3DPYGGzq3WaypJV6Dk":[10454,2057],"1s6SMyB2v6c6XNnPk4xUzY":[9841,5773],"aE5PpHFQX5cbXa6BczV6dc":[-692,11480],"wyC6YaK5FKUK2LVSTCzBDs":[3142,8390],"4GBuvpe7fr3eymbPyUZ9HS":[-2183,15989],"axGP9LESz4AQHjQxHZV4hM":[-1569,16551],"rS8g2BQPnkaemYAppSzMW9":[17154,-1461],"mLcDwqnrHocCXNDYmBciR5":[-7666,11244],"4FhQ7RfLTg9qAxcbaZF3eM":[-11,16490],"1eGyK95zJhwaBLbVouT81W":[3659,1484],"gUikGLgfbam67gSLeN6Lmr":[-14453,-334],"iLAoZPKuhe2qksej5SKPfq":[2441,6912],"93sfah34ZCJ9b9Nus1jnbZ":[4228,6394],"3U4FgoUqBJ3d6w8x5QARhk":[-5722,12508],"szAXQkSWvQUCgZ6LwyhZGQ":[-10027,2398],"3nxb5XCEmTJ76YLzLPrA2G":[-8503,12445],"ds5bma68CW4onYamuP2gMU":[-1566,16301],"nWm4LeWobRrtkxoLCXyc9w":[-5973,14985],"2mwNpctHJ3NgwdKeJmLHRD":[-10833,14121],"jX9Boz3DTuyJwMhi5LbF15":[-2335,9792],"h9yF1m1PK2yTxRgk8pQPMQ":[15791,554],"iffudBag9ACFeBnjyaroBi":[-11060,9490],"3MfHWqfhBDqRDfUbSQuQcV":[624,12560],"1qQczyKLv4QCRozPmGBKsW":[7433,7995],"vQNWNtBBDqEJMdtTgjuxX1":[14102,1242],"j5H6DP4D331BPkEZ7xVxz8":[10812,7063],"1e4Eef8D5S6qh76MLVEMN5":[15126,2476],"iHX8nQ3fqjwQiH9ZTmqtKQ":[16181,-3617],"83AKHuBhVjJESi42tN6o5H":[-2064,11809],"6Rekc3vZzT7eBn46yHGhpr":[3911,2079],"p7RwTcsxgozCRSBkWRwvD4":[-16915,-2466],"1DZNziUjNKLbWxTb8AXodV":[2952,7421],"nBxvHFDHttd6fTLDTsn1qN":[3436,6023],"jEBEbACwHeUZ4ZdtCYWLoJ":[3320,6330],"sQuCJZQLt2DFzQF9NiVNcm":[15084,1383],"7W6riwM33aJ9tkaRZWijVT":[-1344,6554],"3XHFEdQ8XbgVeGUeSoLe9e":[-2350,-7218],"vqDwJc6EwMCaafhooZAXAU":[16625,973],"89XUjKFpWKJZMmtQr7x8Gy":[9901,6143],"8ppWUnpiQs1tZ753eB6GWD":[-12929,5821],"nQtmviy3UDvk2dmGAUxxxh":[7950,8078],"o9Fgd2QMqoQmtLDuobCFVN":[732,15813],"wwbThDeQ5KvSnosSHkPzMC":[3453,13007],"jpKHxtLQmxzRAw38Cq1zTD":[-12514,-2464],"u7rcfSsEc6vcWXZurtMmqa":[8875,4568],"tPx2zb8ubDCCg9kwnk2QWJ":[9987,6288],"5oM58B4ovFNUkr7HJ6XGpE":[4497,-2282],"xvJ7UmZc8GWyAZKTTQLbN8":[9771,5609],"scP9mrsWbunQbxV87orXo3":[9889,6412],"xpGRYJZVKRUmmPkP86f3jc":[-5004,6714],"7H4xCQ7tFwkrZTzzYDPZ73":[11811,-2510],"wTSLugjRik1qrHVEZsAR8K":[11687,-754],"7ooZc3wUbY7ksAjdCf3NHN":[3954,14972],"r4yMHbDdPwzjWQicPkYWdx":[10940,3504],"w9m16DFjXceZhdDqWJnMUX":[9684,6278],"icXx3QnFsLofejsdBvyBiD":[3262,1780],"gFg29omuV4b819XHkXKy6n":[5308,7407],"8EN3PnVQmteT5PS4r1QGCw":[2069,11634],"d7Pgr7kcrtFA7bRhKnbczf":[8279,7293],"jFYnPRrjyPPukdWTxoB4is":[4237,10529],"2o7q1dg9ch8yrJhGVeVYEd":[364,11768],"na7ekXRVEZspER7WM8caMF":[-10647,13555],"skVweUWgVUzMt3xtVLLfxy":[-9724,14452],"pATFvJ5169kN42E4AjQoFB":[-5281,11151],"q1mDhjR9ZXQhgz6QT4HNoS":[-5825,10731],"9yS5ApdUABNxPXnjTiY8YR":[5004,7490],"azing1fcddejddt2RjhC41":[-9257,14408],"3UUcrSXFckZG4YTU7e7PkJ":[-5899,541],"vKcxkkTVGbJkHe8HC3nNSm":[-11370,15881],"xd3fgS9eRLsXFRfDsaUrP7":[-3730,10528],"bzVqzF9Zy8v5DhCfnYSJuL":[-1512,10963],"hCj17rdK5jPjcjmJKq6yGt":[-10883,14886],"uYM4F2KbG1fNWEW39zWFJW":[-10023,14385],"tetkko35G5qQUi5gmJzWgn":[-2450,6879],"m9TELks4Ra1QyvBPYGftJA":[2207,12629],"1SrqryTmie3V4hotGFFAnY":[-8456,2912],"ct3X6CV2r9jrACZjimhWeh":[1695,14934],"1ccim8kc95bzZ5cuNSpMhQ":[-9964,16283],"2xDrUYpoKYvyKefiUC7Zdp":[-5427,7198],"qqn7KaUjyxQkkWejs3SQPB":[-4010,14530],"txQjpLBpkgwonEdXECqdTv":[3590,14946],"u37iFnwjmGNHGCX4qu7NXV":[-11574,-1178],"uBBjq53jHtb9xc6p3XPQQj":[-10381,-245],"9d3fVNQYkgnj4RcQJ3gyJV":[-715,5772],"jKS9gEfzxEJA44jtQAsPSp":[2526,6412],"m7SrgybAS1SLdewQSsBtgk":[450,8970],"4o54mg6eNLCdbzDJ9Rn5n5":[-1012,10596],"xhYXgq59aGpemZyRW41cA8":[-3351,6855],"geUDmPKPDw9s3TXpRAVTaM":[-11245,13425],"oiAd9U14czc1SUw6Ci9BW1":[827,-60],"kj1yP3tFzUW2yrE29UmpgZ":[-3030,-2934],"n9QDyyvBu8VoNQd3GTC6jc":[-10771,15131],"iZobHkCDRPy9v2U4VozkdK":[6793,7150],"3JJZgp65QPdbxQTcSFKt8J":[11357,4237],"iwwLQ1xt93fGbcB2VKtZ7W":[-11758,14032],"nzWNY4hHvWuS2nKLyT3jCL":[-9125,13927],"p5rxR3h5c6hVC6cxAp3hS5":[-9187,10539],"hMQ9YV2Mn7yCRV2KQggtrs":[3734,8545],"8p2US7iiVys8eq2VvBENhd":[2435,9661],"wa2BhQ5FUjLhwkbwS99Cxj":[9364,5679],"6JzefrCnkVAVRbGh1tr9UV":[-10712,15365],"jK9J5f3j3YXuHthqBoFqnT":[-10696,16614],"ku5izNUe2c8Zah6NbPqGSm":[-15140,2463],"8ReCg4gYjojECMY4i6TrUe":[-12212,15524],"d5NiUAHNVchRRyXgekfdbn":[-4329,2569],"3yFKg3oHywUKHCYNVNU4bo":[-15774,3249],"gigdZpuyPVRFXitQ2RLjx9":[-576,-8895],"rDDy2G78sSkyWqu3voQiYG":[-3034,355],"jrv1Qvzi99z4V6fM3W4xbi":[-4309,6881],"mvcDUk2iJzaTw9u856prrb":[1424,-7669],"kzWrzkWCHQfeR4R4sTmpJX":[96,11331],"1qdhuvB928tCvVuGJCBJPs":[-14910,4845],"4K74L4qAynAAX6w1yiD6Tu":[-7395,-12392],"8oarJKCXmJSusWWGFTqp7M":[-2339,16632],"woBq7T9rpLqpKjURsd2R6v":[-5636,12092],"kvL3Uo4SHVthY2r8iSvkhV":[-5583,7388],"smb495qec9W92AKQ3muAmv":[9302,5512],"hmM3VMo6ad6YXejFpkyVbw":[-12004,8706],"9PeL9Cq7kxaktUdbA73hsc":[2300,4188],"wHHt9qz546yog9fAMNm2xD":[6967,-680],"aYeWVdmsya7ixYKkj2XpdJ":[-16675,4006],"edyM9sAc4Z7vCANJ4ybAkE":[-17393,3756],"1FoX6nXGb25i7s9MjHPa5N":[-10228,-2335],"qvHUaMK4D1VqVjr2sa47G7":[-1752,-3519],"1K8uDqYDVM28GGCcGB4h4Y":[-16822,212],"twbTMjoEd5cMNcPPjT2XjX":[-11715,3357],"kVRZ68puaEhcV49ek7xhrg":[9661,-441],"5umX6r23o8GruqJLcibg6a":[-4974,9374],"8HpPARxp9qRCUNwo4PUrTT":[-6309,7464],"c741XxMptem9Hk38skQ2Xe":[-14155,-3308],"iKSzR1XcxEVDqbQJqDnQxt":[6252,-8790],"6fwy6QFmyMhXY3oHHYsMwA":[-11349,-2314],"azmXmCMjACQFg1U1E6txVk":[-15971,3677],"8GAZJyfKFfBhKzYg7wmaUt":[-10108,14644],"eDWwiCMfwqHJ3Xuwy3GB16":[7891,7091],"hXuuH6vShyskigcYVy4GW9":[10031,5897],"vARPJ8BJL2Gs7amY6cGTpq":[8701,5304],"4mEMvprMsPzeKss3GeE2vP":[8248,5735],"ogGXipL5xUdrLtJgR9h7hY":[11488,3706],"9VtyYuAci2mLgkoSBmFvX6":[7787,6527],"gMwejgGWSXR7ru1PerVyYp":[-1120,1794],"jTtX9jFMdhtizAwa4csuyc":[-16946,3130],"9yeLFrjaKrxRyHuZDYX7fC":[9542,3443],"jVTquUBTLCxEwJbh4CxweK":[2256,14632],"mLsM9hJS7ZeiJn2hA9861F":[7866,4911],"mthyVD7ofxzYR61DxesUay":[13881,3985],"jiSpEBeFhHinty3dhHLYHb":[5919,7195],"mJLEh23ajhJ39MwJqF4Muf":[8050,4380],"8dqkDE8f7wVs8BtPguynTe":[7103,6159],"r7NbrvhwwnHaSU7VUgCsMN":[6958,5543],"wted48oRF7UgAHheoPzARk":[5790,7438],"qF4LPAYhHVPhiEz4AEbswu":[-5558,-11026],"toKfjDjnU8jmLDWj8zwt3w":[13188,4102],"hWL7vnA3LYP8987YCANtWn":[-8045,5903],"nCxBeDC7H9DuK9oNwGqXGM":[-8674,-698],"w82rq1bzDspgbHgaFgRyDm":[-3616,2746],"wd3BmW4vBoPEDvnb1JyLRc":[-6044,7275],"xfbMtzfXZF3KngE2mAQUaN":[6192,8220],"gbeNfQAm8AcizUtANTdAZA":[-921,5359],"agn4nQhvHZm5ZwGJQCrLDS":[1911,12817],"ot5L12wYBvRbsUCN5uSdjN":[-2857,8726],"1LtbeDX7zgrgVAtPVsjvB3":[-752,8957],"mnJLUDaLtiY6Ki7cgHWc8X":[-1602,16430],"cxKBzFnKAchPeWcG2AuWoS":[10196,-4209],"9pWySnuwSRw6aABa61iD4m":[10775,-739],"w6ao3JRwMpmYi8iv2dUhp1":[55,-6662],"saMNcP4AuaKYVdPxYbJCiJ":[16572,2109],"fVFfvAe5GY22evFdZMC8VW":[12527,7137],"iHgCgak2KpeDuP66NKQ5M1":[-16854,2895],"p7Tvdmxq6H4jmwvnuMPMwE":[-16688,1175],"a2T2VZzB2nXzHVZdK7LjL3":[-15510,2265],"w5u6NTcep8HWouNBj19Xu2":[-9018,10063],"aCaEqW2mrYCG6y5Gixq7Ru":[-8228,9172],"ankoPUnnheZVjrruWbeMCu":[-234,16738],"drjEbVVvXeFdELBcqdB4Uv":[7252,-242],"gashQqp5eC9xCRMGPmgwng":[-2535,4522],"s9ZQvEzQoNAySmrT8st9Wz":[11935,-2366],"wLgZ9StKJphpyWnXqJAi4A":[-946,-1432],"gmUCqajGxzibUVdJLpA7yj":[-14840,135],"1KAm6Ew56oGYsxTGg5Gpdt":[-14368,-1068],"6fdvHDQmHPmSdjdSeVRVkD":[-12762,-5608],"pVqraKNrrtcTxRSGmMEVj5":[-15871,-639],"vuMocKH9xayFKSwByXDFT3":[-10226,-5785],"6DY7L94CzXfuTYKRatY1nt":[-9564,-2199],"jAJA3WEpame2da89skYRf9":[11725,-4157],"6PPPHESFB34LqspiMYAgTq":[1640,6730],"ffxs36mHE6N6odR5paqZ8s":[-950,3584],"3XAc8GGNWwW93wcCJiL1qL":[-4562,-8764],"f9acCKzPvicEgjpmyPsHw9":[-15913,2917],"oAHLxP9JgBE4cd9f8z6GHv":[-16845,4333],"dMXATd15xcFrTwFrvYWvYu":[-9525,-674],"dkiHMaV5Y1ujBMWg4TZZGY":[-11127,10207],"7rjECF38mqi1LmUf9mr3eg":[-13986,111],"aJhgoPRTiURBvRUQRWUufA":[-11822,14946],"rdnuvd3Et45akxE5PVAfqV":[-5507,-8028],"eSaokp1fWF9jfGVSNfBTiB":[-4590,9817],"j56nzMNHfBCrdP1KEJyJ4f":[27,13295],"waqM1DaJcpbxAB8vC3fJYG":[-461,9090],"avcgrqasDvttuUbU3Y8ids":[12092,-4510],"b1ypywSzr1Pez13XQWnv4f":[6513,7709],"8sgTHSPVXAN7ckZ7fW6h21":[-17256,3962],"hCwe5k9wRBxK8E9KuWZB1s":[9150,1922],"jb4RA6soSHPoTiyGS9UFQJ":[-12420,-4596],"tpFrQdk8gqiUQnvkzpfk1e":[-3563,11626],"h5NoAPoYF2J13QxzdPSu6Q":[13582,5529],"2CaEQaygeSug41DGzmYkZB":[-6374,6040],"dneQLQGZkrYCrGpPj7znxR":[1754,6066],"m5tXqo45tRAeRTgTYbDE3g":[9767,6535],"1EtpQeoci5WVf16TwaAGDM":[-4329,5479],"dwJVxf5rd59ZwfN1ZPK9db":[-1390,7413],"3H3vYgfc9xrcyJRYAk4hxU":[-2677,8187],"saCK9ATp97Nrptges4itLR":[15067,-3876],"cXSqJB3rZ4Xs8ij6kkvNCt":[13598,-7272],"dk3PBjr7hf1C296AGLiVVR":[13115,-7707],"6HSzbWkGoVJibWxyEbt6t2":[-12397,-1449],"hQp1o79PvJHDLreoAP9C3w":[12312,-7702],"7amF6rNZkTFvG9uAwMTPbq":[15024,141],"w5JgMxTdoR1ntktyTKAPNX":[-6057,-13458],"mpiwS9XcSDfTUy93gBZG73":[11457,-1108],"6KZCwTHvo5tPCUccCxnDjS":[8325,-1087],"oU7pG4o1vdLpkUygiMigf6":[-7038,-15524],"8zMq7WrRxEczPUy88vxqXx":[-2235,4683],"sKvpeEgAC3Hi1qa7zc8EvF":[10755,2297],"dRAMmhatjjxt84oNUXRoBU":[-8317,987],"ouTkRoZJYWUrTgUzSiGgwh":[10071,5607],"rZNZRKkXqRXxGKE7n1qput":[8329,9796],"nrq8CLDQtrxqxbSRaoEKis":[11128,2502],"cVxMmG4hhtTqF5iPYKLQ27":[-11853,13824],"8RdvrFDPCFQXhp8QZ3L6wJ":[12682,6336],"xzmMQhim39dQ7JMHfJGQXF":[-3458,8112],"vroxDCNCsjCLJ5SBevFPv4":[-6465,6898],"oNKvKKMPM7thByyLYvxY97":[7094,6911],"9gauas3GGwnCFhUygw6xxE":[15303,2116],"97XBGwskfALVhm4L8HZSqU":[5965,5924],"gM485KBC5mvSQ8x16j3AsL":[-17324,3476],"9LVG9otzhWj2PR3KE4rKEe":[-2721,13821],"ns1LGWbuhN8mZfn8GUP2TC":[-2633,13654],"tPHiGcjzMnWCvaLn3PHDoE":[-590,17258],"qRAap446zXYqtNUhkz6dv7":[1374,7825],"2NzNZMEJVtCz73hkTQzuob":[197,16206],"7atuiUcUmp8YVJbx5prVbe":[-16673,5559],"3ayr7nWcd9mMSMgG7DFaFT":[-11672,417],"iNTCuMZyuFxCjRw2mXw7Hi":[1761,15363],"cCiCk5XsShsntN6rfZ4rL8":[-16533,3857],"3tuZDUEt8azFjwGfzj3EeB":[6223,-4308],"65SNUFLQgSxZdFAYZsVLb8":[6022,4404],"qiZGyEat6gcAABvecT6cHj":[-3105,-311],"6HpwnMAQiKvM55ya9eAwnf":[8441,-4562],"rvVoDHxcFKhPNiAfuCk4By":[7282,-3908],"ueGqyJ4qgqvv2kYDw918tT":[1398,7171],"uCifiCWGgDmbczQNfmXscz":[13101,-3552],"5eWhDXcuo6vhjzvEPCfSYj":[14087,-147],"8UqFDRdBdSHFz3AuXDfJaC":[14177,667],"hQ4F4aG55L37cXinH5zvSn":[1747,-11932],"1HJGeovzBKvDUzkb4vWDS5":[-2432,8531],"e5EjCRJv9e9mY4fnThcAx9":[-5350,6026],"tcjoXuyJ3aTX61qrq3J6zq":[-9054,-1349],"6QmcL1wFNr5nKTxsxF8hqw":[16435,-1724],"puTvJei1gsKGjEt9nDjv4R":[10594,-3486],"suHgPULLPfnXG34T23jcvo":[5992,-3739],"5fTCQPDfV4bkeD2RzmW28E":[7099,-4235],"4qrwNLsqBkYGhcWvRjr5sG":[-374,-8660],"bTZLJGNX6PrsDmu8bMsa1T":[5678,-4939],"2imU89Fxdy73FoNkBJpUV3":[6280,-545],"6gy6Mm2LmipMFzL57ghXVj":[5486,-3977],"vsj7bFoLZ3ZfPXENkNJ98d":[-13177,4916],"pGSqCBWNWyLsK92JBcFbT3":[2101,13450],"fNJ1jMB2RNoZj2RYs4cC4B":[7202,10627],"hJaspzx62GX9nFRQBDhvY4":[9414,5837],"gGbqSA7DrVa79dNjNz8ewG":[-7826,-9971],"6qYvnUCFpBPNk2PCS5kkKs":[5716,-3868],"xhB7rx9NfZ211145DQoDY1":[6359,-4771],"63pBQhVP9HAGx8WwN2kXVX":[7599,-4079],"oKHNsYc7rHcphgv8B492QE":[6525,-4454],"wjYYdeAYb4zttZxxivHrV9":[6931,-4323],"eCFk94jPHN8PW3K1ytQsRG":[-11679,5422],"aUWZzpNAT8rngdeXydPPeF":[-7030,-9354],"e6gJeirYcjKuRh52NuvLTr":[6702,-4378],"gJo3wsL6fuzmnTsGX1vMLn":[7094,-3206],"4tdNy4rNRR9UzQiih6dYGm":[5998,-4451],"1Li8Ecuif4xmjs3kJGWRcU":[-7285,-14534],"oxDLBRCdRikzMmZ425xo5e":[-4632,1955],"czw2kfsCZ1LDsf7MuG7cQF":[8573,4380],"fB594HpqgdUGq8S9hBgocp":[5043,-7088],"iLLfsLHHQAgRUTnSNkbnv4":[3875,-6807],"rHZohMV2ipVRwmi4cX9dxk":[4941,-6455],"sx2WamkGgu7kb8MW3VwsKe":[-9728,14869],"76R3dXs4zSGVvWticAq9PT":[-280,5933],"wzQarZGKW68bCAqxwAtomB":[-10265,16171],"oiNvdfz6VrzVsGmLXr46nZ":[-9616,3946],"eZk1XMuMGm3pVM8opWYZB6":[-10557,13925],"3qp1CCjPuPTdoLb4ViCTmh":[-10061,-12114],"gCPnrUCJ8qiRvsLD1CacqX":[12876,-2265],"mXPZAkpiNCXr5EBLTNYcNz":[7449,-2129],"kRw5egv6HAdwfvgAi6fFWJ":[-13522,-5069],"sKzQ1xawvtB9e3446rF7EU":[3612,9448],"hup5qHfg9Rybq8xkCzUbbz":[6980,-7861],"hQgBKLxmXHHFxWcGNwT2dY":[-17519,5021],"2NJyabhxxpiBpgqr3YKPcZ":[-11168,192],"iA4JXePdHbZ9jib66BiYr3":[-286,4972],"mbV9Yic88aQ8W6fNWXZ7JZ":[-11590,2818],"2kVAZE4KxxrGBcJg5hPim2":[-10021,-11871],"63PJ9Go4vqvV4opJWNz1xt":[7260,5572],"etRr9vXE6AWAEcLoUyYi2W":[5061,8019],"4ki4JpoBbz1HPgNso8YqSa":[-10023,2224],"ryUtLdBoNyTcUbhUKFPJpe":[-7229,-1312],"njiL7FVSKFFYNebAp1JE7U":[16129,-3795],"x4j21kfAA9SKSZ8RSnsAZ5":[-3395,-3124],"7BHnJHaikFe4YXkhr6sgaF":[-1849,-8632],"8agtBkrtdSqLCHj6E9ESRv":[6792,7560],"3Bi3dQNWys5yJwmhpvmmxR":[5140,-2774],"6wEBvoSUpyJx7jh6BMbmMf":[-9918,14129],"5894gvUG5FFifBdqUwE71v":[-9608,-96],"iRFcLoPKFkuuvyis4avjmc":[1381,-2178],"h2CjRwXV5CE3gscET7zARB":[2233,14221],"uK2gExB8EiD5orBSobxxF3":[6504,7160],"n91Etq9JKSXC2QQ6SgAXrZ":[-4434,6604],"9Z21jRdJ5wkJDN2S2vVTsV":[8402,-3902],"wtJvxcFiGUnDNwvgbyPhkY":[-10942,13558],"qRFzg72Nx6u3YNp8bnftap":[-7404,2878],"uTsLeBSV7gE5niCSDsKJiS":[6453,6212],"s9DfZkNVTPemXLbQV8yT9K":[-4726,8457],"6Ab2T5GLw5sK6eD9XmnGke":[-6393,1699],"6cDsGFhog8sh8XKWfrqA3R":[7866,-4125],"mqGtZmufS3YVJxNTqVFxzb":[10776,-4085],"qpdujgAFLq4k1Ji98Zek1J":[11790,5165],"5nGhicN3u7yv2i1B7fyjg2":[8894,8017],"83p8UyRNSQwbuPFCVuYkAz":[8600,3155],"7rao9cs7UjZr2EN6hWSD4y":[7089,7408],"sDwPHnWULd2hjyik9SqT9V":[-306,14808],"msTioz31f7zmon4iA2aL48":[6208,7251],"h9xeK7YPL9LJPpNovgLd6V":[6130,-5039],"2RXsHEeeuWAv9HcX9aDR2f":[13389,-7067],"dEVYS1sJ1wkDCcD51QiDuv":[-6732,6424],"nC9UnocjdtPcJbPKu9kj14":[-5110,-11236],"gnfDK7zwye8fcdjU7GoRsq":[-7080,-8990],"bJxiZrRYNErX2NEuCVXGa9":[-2693,-12611],"6tFwGE11DU9MixeR3TKCPi":[-5681,7855],"gnphfaxkczuQhbQFVabMS5":[9942,1979],"egsmZ5fkGjhujobqCezz91":[-1613,-12019],"rK1put3fYWePRhpxgcdmKj":[9163,-3724],"mUmga6tzQPF79HAiwfybnH":[-5400,-5392],"enAPyQabDeUfUkjcbrJWYS":[13381,361],"t6dD2ZfmEkL3EpbBb9aDpr":[1471,14464],"wXfKbx3j6ERLJvFzf63hYQ":[-17592,4669],"ggpbok9yQHZP4Jh2drV6Mu":[5213,8726],"j9B359L99kZYKh8ZZg5id7":[-2111,-9038],"ik1H2BsL76wXtBgdzgrkL8":[7184,6282],"8ZoVwRZnoRFTQ9R48V3EjN":[-7915,12333],"sdVWpYxRz6UWdMwNBXpXW3":[-11563,14291],"jUjtALaboEYMSQsWQzKRSA":[-1839,9208],"ucuDhXujRHfVYB8V4YpZiv":[1363,16033],"o2bVmUdUr1r2Ug1VMv3xUx":[-1144,11031],"sSxeMNczsXZDNmjpXtV2n9":[-1718,-5909],"nVovZ2LddDBCwE3ff8trXM":[-573,-9843],"qncVvvAxmwjDr6gxJ5syCQ":[-6123,-5133],"jmhMpsAEZwinqQngUsYkEw":[-6610,8549],"b2ntfXwmHmN5r1RUAB32YW":[-563,17009],"ibyFcu7bKaTAkJhE1m7i5X":[-1715,3338],"5RjJXyx1KnXpSfzTrMqHQn":[15976,1126],"3rp5a9DkAowUFk7vtvjXJR":[-8549,6765],"f5dNEuSMLj27js6HpWcsH1":[14891,14],"5NggEYGsU8FQ5X8RCG3tWL":[14665,-517],"ugYjDekxqCKWEqGrm5adCW":[-10274,-418],"cgC968fgTdCaMJNoBZVUbN":[-5166,-1600],"tjdpitxDnDgxJkTV8SLGp2":[-5507,-8395],"knztWs1owRVqJfpyDqpGdq":[950,-11560],"orWsVp1PQvNbR59koWvCjL":[14698,-5506],"kYoemw3rGB6WjzMhfJbteH":[14392,-6638],"erevyx5xYmNqvqGCV9kWnB":[-13255,-6171],"dBFp5o69fxJ5vKVatJwpSB":[-5180,7764],"q38mbyyf3G43AtLeWW27he":[-1981,-286],"vXB5BuSqR9TN8PUguVEy4c":[-16725,3754],"oMUsyqB5vGGBodxGGZ1nHK":[-11084,8470],"sRCCa7DRoVMWKWZCYhC3AU":[3687,7058],"nCGVMtMqhGKHYUnuJZRwLy":[2536,6693],"54JhSXVfmdkWf6ATn6eVmV":[-1443,10115],"qxiHRF9nZZJbMxujPMQvLc":[-3635,5730],"1awwxrTX7dF1NFi3pWgvZT":[-8611,11831],"3XFYJ3E1NmD56oMBHi2YHJ":[-5218,9804],"eXapcLmAhDqJe7oKUkMTmz":[-2957,-9855],"aBbjyE4Y5skqqeyfAQnDtk":[4583,2081],"kpiHCNNqZuQo1JfRp2hrfR":[-8251,3797],"hnDFiAbLpXBSWCG9L2gURn":[812,6882],"kFNYhN36P1mASuEhdviet7":[-1714,15862],"bW1rKjRfr2eH8a5VnZKS7H":[-2588,6459],"gEyZDQy5Y8E7qPaaVt6LSE":[-1794,5875],"mDn7dm4aUDM2VZHbfhuQj3":[4242,2290],"jrWyZHCSX6tQsXgxHRKSSG":[-5081,14089],"wQetQyu3uQ6TUcdujcZGdx":[-5354,14797],"n5okxgTouRnhnqBEbi83mK":[-1476,16658],"anQXcTGV46kY54PyfYpdKm":[-1268,16492],"aJZfVkVmLnHdJLemVGJBuK":[-14925,-3976],"uHW8PwR2dW5M4EpoJpdnk9":[-1934,8429],"uDpvVWGmp7Rz4K9t7HKNDC":[-11873,2952],"gBmgWGBFrkTWpY8fhK8jYe":[-14078,-3534],"mhwor2bfiycLN1oz8EQS7v":[-16735,3614],"ak3GmqPT6rL5h6iCKYqp8Z":[-8553,6063],"vx4BhTWRWBXnZdHFE7fqFy":[-17302,4396],"kjVKmeTWGVxwCQpkpnHxJ6":[-17349,4178],"eKPBtL47b9jLcEBrX6HR2c":[-17256,4292],"1tzJgQVvkg3zfHohxzaQmh":[1512,5306],"ugxnS6kCcmxSn199T5ca1J":[1157,5895],"wYF684JNpNUfC2BfP4Yx62":[-6810,8718],"6JMHysgAj5WBHEj8x6NKzK":[-7931,1574],"9E94pfWyV4pLSCJUotFh3M":[-10550,3649],"pierSQLqEcd4y9f8U2FPQs":[-4,14027],"1VHxBMURrT3kfzCo6zV9He":[-2150,-8231],"n1jsxHWcYjz7aPxHuE1Wyk":[-11036,5053],"gDDecECLmN7DvV8tf2jQRD":[-16828,3321],"w7qg1Jj1KJamKSbnkNKYi7":[-7542,-10883],"cF9V5DnNmUhE99PRVw1oU5":[-9309,16697],"uqhZ9BZdwE9nAXz26hfj6m":[-1439,-9936],"n69mntSmkVceAXWrq1GnXn":[11493,-4508],"2qHoXAYcu9VXkmA1u98J1c":[2350,5460],"go6mp3vvf1Fb244mN3ES6S":[-7579,8669],"xg3auce32XmA3fDJgmFjob":[-5075,-11449],"v8TAsVR4oRtnRug7CRL4rc":[-3657,-13508],"iAy18wcX1PMCRJdsU7YaeQ":[5672,6630],"s8HqoTt4292XZTCMya4NxY":[-2852,5054],"5hcmY9HYrZNbyVQ9bXjYeh":[-16744,428],"8V4nrgLdty5A3c24kXp4Xb":[-476,17119],"9jjczkhFoESQGQqaa9Dfdb":[-7847,2875],"hY9pGBDrvcwfRC8cRaCdyB":[-6591,3607],"nkRgM1LMX6Wb5E49tHzD7a":[-3743,5012],"esg1meT96XvrgwjXarzESe":[1403,6880],"qwcfiS5tKoUV1fmihcCVQu":[151,15401],"284FsFrLDiudNHe8tXaxXj":[-1536,7972],"d6osmK6v9vbAj1zeBYzCTQ":[-2853,-6853],"fieuxbMVjNfEV7T5nEa6ap":[-16639,5197],"o6aDbfXsPfWdhyqDS7ziQx":[-3856,65],"23avUXWsZasnDXS1343wUB":[-16346,3147],"92QWsAKqmMSwpjS7jckC3m":[-17393,4870],"hyxFuxTC5SUgMRWT3K9Cij":[6858,2232],"1VmxLMtXq49vaVJcCvA3TU":[9346,1394],"m4NidwJQZta71seT9jrfWw":[7157,1988],"dW7cffHewE53qXD9W8wBzQ":[-9836,7878],"2Q14dVqeCbTGzd7iBzfhME":[-10539,9895],"cbRrMWxSBQ9ZMECaAVe62d":[5630,-8923],"wQ6yG4w6MyX945f1GVjM9U":[-5114,6895],"mrpUmRGf47zQh4wyf8R4Mb":[-1111,15477],"68N1ibYsn4VfJrZBg7Z9Kq":[-16996,5305],"wRJapT4ujJWgvYUUKEWPkm":[13451,-3887],"3LhJUgGTt2P92UDS4s5dKn":[-4590,8227],"1i4KvhQzVVARjSV8hbM3xy":[2421,8382],"1b81bbSthmNH9tvzr1aBWb":[-10064,12984],"1PiRp87rWbDt9jKkvURqyf":[11632,-3055],"gb1B9b9bmVgGxDp3DyR8to":[-5234,11662],"ogie39CkzxUbKUNeRUv13q":[-8178,3629],"5PouETHbh8sBFZoqTDtihb":[-14110,1907],"9wj7GRiHbByUav2wezy2B1":[-272,2759],"bF1mJhEWFhunb3eq3WutsW":[-6299,2014],"47jon4eQd7BhdMCmorKXUn":[1179,12197],"3WQdfkJNNmqVoxNK2iPaph":[9900,-4197],"nPYRZHEWiFo5io6C1MSCE7":[2301,7236],"9n6tVYwF6Fw1T1FkbFAG6y":[-632,-1822],"kiR9Hce6tUpaMQb1axkCf6":[-4363,-10795],"6txAdKDMCCXroUgLfpMWxg":[-7676,-12963],"9jshc7bYriUKDSMS332WJH":[-2594,15920],"3YCK7S6Zbjj97jmy2Pg63Y":[737,3160],"ebwMgUjmopkmvPxggvPAXb":[-4896,4458],"xhCGQnretcN5CMbHDennYG":[-4428,-10924],"nWpkH3qPKF8x5NsdFsW1Hp":[527,-92],"skedPMoks7Lm7QfNWdYrLB":[-8491,11706],"k32hk1TL4CwWrAWsFFDQCZ":[10027,1407],"nPkXjsF3r2rtLhmuPLQ78L":[-2044,-10356],"1AaZEy32jR755yg2V6YEjt":[13381,76],"d2vRXasP1n9qnD4Gnvgmy9":[4129,5636],"4XNYbodkRCoBNU8SohyM21":[10698,-13],"eUjpeAZyV3ZPEzwoLrdout":[10242,187],"1bVdm4AVhnu5cQ7a1AASGM":[13467,-5415],"jhuvBrkiaNznJvXkQRqZLQ":[-2963,-12463],"ttaCimR3s3SEDbMUk5SmCt":[11425,-3918],"bUv9qXhfVNNXrtvA2ip9mm":[-1527,-10057],"tXaQPgw2sQWZukhEzwggRA":[-5495,4542],"xq3duAuSi8KNQbdYxErc6t":[-17312,3592],"5LbfJfGDeMurtfEQdq68nR":[-10986,-1440],"oNBwZJrCWs6h5d534vL4Qd":[-3614,6240],"5F8wU9efN5yCkNDjofQkQ1":[-4922,7312],"nK6JDuQzuLAsvKSk9Kxi3b":[4863,8778],"qo35TkeRLW55oysPYysypr":[5215,9391],"q1meKNtafaJbYJJkfPc2E4":[-7150,-5227],"vA6mRXB7VsrNjCHpg1Jji8":[-2211,8169],"eJJB5KawjfmkYBYH9vuw7R":[-6851,-12513],"uCsZQgxUYUVrjyMZNexXCx":[15196,-1261],"9XjpFRXuP4snqqfSf5owMn":[3701,-5306],"pmci8LWx5is4PXUhU5Kshk":[11546,-5994],"dkCafnZosEJrR1axv8rqQe":[-2509,7845],"k7cW4dUBhdAHdHxKQvuj1x":[-8324,-15077],"3Zz8V9t3Ybqce4zdkLtrkW":[13583,4012],"5fWqzzbfbZW4MwrRvjQvJq":[13009,-923],"mE45yNx158m7bMCKnFY8Tc":[14999,-1902],"iVJyurgbSiSiK5EHRgQi3R":[-1491,-1518],"2sPgKsAAaDDMBhXDyJQqpS":[-382,4540],"mXHwzbj2w7EZR9vfYBoChe":[3017,6338],"jok2DSWpH8Rchoosc7HJCY":[-2229,6222],"iHHC6UWrYp6zQYXZ7BQQrL":[13268,-1518],"dxxxXBLMJua6CqD6karije":[10483,-4332],"hnTxU49mzzDoU1UTjrXuUU":[-7926,-7344],"sUL1xC8pC7y5ssDJhvFpLv":[-6486,-13040],"riokKQdjhooM1pxCsUxwkY":[-2370,5539],"7CA3VFmjeX3kNFbxWXiyNr":[13179,-738],"gp4GwT5mev5QqAKjQJT2VQ":[-4307,-4315],"9K86yPqgkGc5bh1dWT1ZES":[-3023,-8720],"uaas9NGsVJYYQSHsKxKRoA":[-10105,15947],"qTd3bDcD8K3mBJKHCnriTv":[11145,-5248],"nRg9ee8JgKVqwf5BrNzgqh":[13541,-6582],"sqrDLVBrbrFNyAcQfk5ddn":[-13174,-2641],"dacULgTA4CX4inR41Azugz":[-7138,-15789],"51a3RYgYiWdi1AJDZ7BazY":[-9462,-9250],"3hg4aodLYTvg2ZjuizdfbB":[-1699,-10665],"giWCn7PDxvkTeY35JSpw1M":[-11135,-181],"pk839pKQtcd1musAa2kJhz":[-4995,-4272],"qPQW7ty9Z1SybJjSNaDAoX":[13021,-6431],"qnfEauRWN6emMtGC1vyAnE":[6646,-3638],"njrAof9G3MEter8ECrtG2F":[-13201,-160],"2CxAzxdbWXAdNcvXJB61V5":[-1039,150],"38RzFdxVQWNFBmRfjKKQpr":[9735,-5284],"nmA5XKomBszqex7sbk2Vm2":[-5382,4320],"4NKT1FJu6cS4BRoxHrHhsi":[-6264,-7793],"iaTrrGxnopY1qGyR79v9nE":[14822,-1224],"qDiX5WCSyGSPSk9UAVS16L":[2896,-7388],"wdXPN1w32wVEebQAmd79Ln":[-15547,2941],"rsiPGZ9sTcKp25SdVvg6wG":[-13930,2547],"iqAc4ThTa2Zp3bnrEZFa9m":[-7053,-14745],"qWBh5kemgJRHu3zRUzSJkW":[8011,-4918],"rhQ18Gwns79c1uHEBh7B2i":[10589,-5144],"nwe5NtCa6DimZbt7NGZr57":[11240,-5830],"dx9Aw5JPmfBMouDLpAHRiU":[11847,-6620],"nK3qQuepXwQHxhMNMuZscZ":[776,-1920],"p7VZ6d92Wjfh8w47njgoGG":[-10348,-11220],"rF2UXxxUHCj8LeEWhWZHWe":[-1996,-2888],"a3mE2G5ag6fF7SX6qsraJk":[8150,-3996],"1CArre9QdqnwRdwnuhvs3d":[-10676,-11370],"efkozE11jVptYzsvA2kYxu":[5027,-3658],"wwSxupHfjXMxn8QsbEeUE6":[-2852,-3462],"qyEeSkPdWzXvLrcu4dvUMA":[-3128,-3392],"fQ7bReK9Bx2HqWeXMaCTkg":[-3577,1131],"1bRJrE95wPhGmMxz7fkrp1":[9331,3940],"uARSn7znEc82LVUfehm5qy":[-963,-732],"r4tF6g8XvhZeZvmgjVG6En":[-1249,-1058],"wQbeHSPK9hyNKVhheYFwrS":[-1965,-9972],"9Csx3Yb2hKPmg3gAn2xuPS":[-2763,-11236],"fLsSF3tbt3rNZVqXjNg7Be":[3366,2954],"b1HR4H5uw7cQ22J9JHjaN2":[7057,4197],"7Rr4F3wxVUojqnoSCX6wQz":[1206,-2501],"3xubRgMvwsj9VCoayd7vRM":[-8001,-12182],"sr6M5oaonZtT4UwzcWBsTF":[5580,7194],"sX4YZ7UUf7RtyjhoE6WzaZ":[-11017,4238],"1zoxt2AsiVoKL2L3uxWujc":[-70,4719],"ngvNKw1Wuh8mWuhEWkq24G":[-6388,4097],"1FUihwRUUapNzjWFBWEovP":[-966,-456],"qRB5HgGpxaECFR19VHaygo":[-8094,1686],"9Nz3uxRMQP82hNzrfVzBPd":[2860,-4740],"i9X7cLLZHgwsr5smXdkHzU":[-5206,-7841],"3mGJvACFM1fcmV1dWEKHg3":[12700,6764],"riFDG5e7DwPP7XPR1TuWvZ":[1835,10042],"kwr1Z2EFNqX97Bu2vQTRDB":[-62,-4328],"pQYx2datTwCnQZC9ttkdfY":[-3253,-13206],"3PaY3rxexanePgp3JoW8gL":[3142,-4388],"okp319EF529S2CwJYaCbvr":[-1365,-694],"66vv5kdJatrc8DjB7Dqx3e":[-380,-4349],"tTb8t7eJnN9eSbpXknu7se":[-4878,7739],"8kRz31HSsUvaCRb2BLsY8U":[-1536,-998],"nWjFySHnFFS66j2jxaMD5E":[-9164,4625],"2BDfdt6M9Qdi5mL1i8Q7eN":[-11193,2505],"h4mGekcKkBKFU7yBzRoD2q":[-15084,-4235],"6zaMoB3A312jDUa5N9wM8B":[4194,6520],"mbaL7CF169o8XRJ91NrEm2":[-4603,-4104],"nfHoaZPyYXZgswExc1MaNm":[-3698,-4718],"2Kx5SG7GuMYnKzxGqhjwak":[-4012,-3325],"wHpK8x1C79yAbXYq5LkzhL":[-1960,6042],"6nfT8iYvdxTzC8Frt33UUa":[-2313,7385],"ptgMmiAqr2mQeQTTba4M7e":[-2163,4300],"bWunAGzWUaQnH2r8jh4wGW":[11,-3459],"dU8geBTt7ReHmgQzSwFc2J":[-7318,-1663],"mJLE6HKYmCUNFtBmcxT9qW":[4124,2715],"rFVKRbX9QTCskoyyKFymp3":[10001,-7978],"3bExUeSsHwtd8y36Zy4YVM":[12798,5],"sRo2EjCqiXG2zQbEX6vQLe":[14055,-5102],"3QmAeDrV2KC4efWQU179GS":[-10377,-11718],"2FjL8Tm1f1ctvXsv8WuHvW":[237,5077],"bKiW1d2mDwbqnxqmX2A2Nx":[-2559,-3528],"9nsPFfNiRpmMTGAi1Hvuar":[-964,-1005],"6Sjc64pjarvf4bETuT7uMW":[-7696,-12393],"m2tDt1qVghZZis4KnHHYRP":[-1376,3181],"j924yt61eVZPwsrCSc4KRy":[-1696,-11545],"7d3ba6pFKw3Wscxh4vWYTF":[4797,-3560],"4EiEkiwJChTE9frqdXYewG":[15518,-5454],"kWyRe56qxQTbxNrkTBTwwR":[16217,1413],"pVjaVvicCKq9uC2eyujNJv":[-5582,-1710],"49TKbm394B3ynTTLnWesAX":[12830,-1224],"4wZCtNo2VJ51qNgMzk6Y8m":[-12889,-1969],"pTdTLwZJtW5hznGzYTXup6":[10483,-7138],"ht7dmnTN7SP4JnHvSYdrqS":[-5293,-2814],"tbm8fBgydvj63RkuxYcrR7":[7823,-6689],"wegCAhzWoX1KVJNsMkfsrW":[231,-2843],"qLS3dnrd1udWvRZU7o6FUy":[-5644,-6979],"sg5fDNvD6avWJAFkoZsfNZ":[13754,-5374],"c7nRGgyUQnfzhzBt5eS85k":[-12580,-5477],"5iXeTnG2yMLroZBUaoVm6t":[-375,-594],"gSjF19wyLxxsN651ejHb6L":[-1250,-3621],"dHCofiFKMFV8VJFbWNsrxE":[-1218,-4625],"9AC4nstZXKCJuU2mTYA6SP":[-7033,-8878],"b6D4XjTPM6KfKUkKX1ExC7":[-1393,-499],"uo4faLzhFB6qvATwcpFiee":[11836,-7405],"4rZFR1dP2eUcofm4RBJcEr":[-14706,-646],"o3FV67ZfxtgE6hYFvdRDWR":[-9674,-5194],"8G5fcDahM49JZ1yNHr5UWi":[-10748,-10304],"8ycB39PAMJgUKrgqU61uSD":[10855,-7716],"dx17NwBhSLB6x9yqQiP4hL":[-1120,318],"6LyDfXtqP27oNeSNNKULkm":[12745,777],"pqEErXxbmLt8dM6ZqSVECY":[-6991,-13343],"rx8WoWCvyvqdPME7YuZdT1":[7793,11603],"ggfTkHmv8zBwNEvoYdJjud":[-4572,-1196],"pw83CxvjdWnDkA2JWiNnip":[14350,-5597],"5PMv1Z8N9pc21y3vM6yGS2":[-75,-366],"n5iY9NSsabAEJSFustuxGy":[8917,-3679],"c2WEfiHYdTtc6d11XFr71r":[-1570,-2921],"kkHQTkjf6teWgPi7wiCerG":[11073,2779],"ikjkEJCyAuMJd9bxhQrCkR":[-1196,2595],"nNL5J1m8ZxZha7eYGPzXuk":[-730,-3887],"uGHwEJVYCao1cHNCqcdVwz":[4543,-3703],"iuGhBxJCw2JdXiQFArXpgk":[-12701,-4764],"qNHTJ92Ehgoah37x7ig9DL":[-3898,-11186],"noo1miUggyaVZ37nG5FcM2":[-4700,-10566],"6TM2oHbyqr9z1vaXNCHWa2":[-1699,-2754],"9YVheSBYKEAN85S2CSeGxu":[1534,-5916],"gVdBA8qo5PEhJQw7VrvmZu":[1641,-812],"5bTwMMCgDU3zCFWXzWTsBQ":[-9131,2491],"dFCWftzgumG1qXqHY8avwk":[1024,-308],"i9JkQYffRkAvWf3HPgjJXB":[-2446,7523],"dDVtEnUobs9BM6sG4BJamg":[3457,-2834],"cW3tQUBLNCWdu5TP3evpCE":[-3631,-13845],"7z7eFMEbUiRfEdGtxpBXJo":[7848,11718],"w2uZfZZaYLbkBrVXHAigCy":[346,14541],"8qdg1nV57Mi3ujhvToagYd":[-1223,5278],"uDkjWiPBnBv1Vs4325wWdm":[-4241,8699],"7rpn7LP2vR4hWmGE6fA9BL":[1394,14221],"fuhqm82sPaggGPjGcMpVf5":[-1388,589],"pWd4Vf5GNWauQGEWZ1FoAG":[-3632,9877],"mdJiX7QZDGZyvXUXHPPD7D":[-431,1137],"84EPmX2pVBfbJAZDgwawau":[-6277,-5556],"se6DdcfpW96yJiiuuotULA":[-12604,-5836],"2JjnZYRi2greqUVyquSpHX":[165,1482],"7rZdn4CAKDecWLztJjS6Q5":[-4906,-5006],"w55YV5vHisdYqMHWEg59Da":[-14,766],"jBnYdBvXgPTK2m8KeqJNB7":[109,3547],"eTCfTbCTSQAPj1HsHkLAU3":[-3260,-136],"crfdocMMkNRdCPWZjXxXdA":[3718,11346],"jT2atRFEcgYKX2mYt6KBfj":[-1943,309],"hA4kBitGD62fkJ1ZKvkEko":[2272,-4157],"aq64NZJA8NxW33qLKwnKiY":[-2307,-1561],"qamLkhwi86GQCTQvztKAcT":[-5348,-15407],"nkbecYXE4uarML4TDRmvkC":[-11087,544],"h9qrfys1GQWEtBJuJQmG5c":[7706,11931],"7U8q7oPQmZ4VM4RuUPXCtT":[11839,-4002],"t6xdonwsPyHLdsxk5xBHER":[-5569,15240],"ug5GQxDxPNTXNfRqCPCusq":[-5332,13126],"dyrqHZzvtMaWaDcngvPp6C":[-9094,-272],"82MNcuvkELNhmfmMBuoGPz":[-9068,14087],"acoFEj6vSTcrRuvHJPZtq5":[-11115,-8602],"fufqKpg3jhz8cJNYv3t97M":[10782,-7130],"tyQAx6swXje81s5VSnbwsZ":[16059,-812],"fUY8BoZbog2SmwcNtQw8rY":[-4348,-6572],"7KAcKkmzwh7vrtgEJibKUw":[-7720,926],"i4NV4voRtNXf7mw5nJyuyj":[-8142,6588],"cS6h5DdJJVvJuHpTCK73JQ":[-8790,10497],"wRyVXGP7NjSdgyJ9XArdGD":[-10965,8860],"2a1Bi3ym3XfuwvgP4oTBZB":[11187,-3324],"mxy79y17yNyN5Y3cW7ciVX":[-1932,-10782],"8FZYvezhTHHLWZWeyY11yp":[-5163,14441],"qfH38bkqupzpWPWpgFk2xG":[-2213,15731],"wzMGLvsGY1cdZwRfFg3EYz":[11035,-2455],"jSybMp5zJYJwVuCqSCB1D6":[-11176,1640],"gko46Dr5789pPRHzjp5Ndo":[14662,-5765],"ePt5FZEgjBMVcGUBpAZVXB":[-5795,1943],"edk1jZmBuuWS1TWsYZ4Jjv":[-11773,241],"iYhwB9o5ZqcqMF4qV2yn11":[11331,-2392],"8qNavTCkHdn31knuEYPYHj":[-5635,-14439],"4BwQR8NSitR2nmA8VThWcj":[9267,-95],"9ZCGvdXvb6nytyEMjkSef8":[-5545,-1048],"41KxNvkPXA4Aeo81aNPyLp":[10067,1203],"nVdKsWc9QGh2yvbpqY8bck":[-2660,14021],"56ATRBMeS6Z7vAhwcQ8XtP":[9978,-1012],"hynvhoof7YDYCu6aJe9Kcr":[608,14933],"qYvut4QUUyWyHnkMmGDcGN":[4148,11207],"2iUinV2HFfTDFPZjeLyUya":[16008,-2902],"hrQC6buC6TvAeagTaNVMgc":[10885,8234],"cSmdVAfZQ7wPmEaSiWcLLt":[12681,-4146],"w3SLbM1n99obzFhhALA1DV":[-11071,-8379],"cn63CCvbe3c3ahvnPWxWYx":[12303,-1313],"7pdMdAAnzNaTQrVxGNECt9":[14049,-5697],"bipyZw7GpVLBERLYEC1v3k":[6186,2810],"eatTycWc6PsRjwDPkc8gHq":[12338,-3518],"kFUkoPgSrEqnwdhQxGGhVM":[12687,3457],"bwNbRG4G5LGuvS9zm4CRLD":[11159,2174],"1t5rC91ujXKKaboSF7zY9G":[-1102,-9922],"kQkyW3YzioYjBobQa6scWz":[10142,2223],"vnnisRpiKNGasYCUMeGf1L":[-8346,-5330],"9U3YET1FLRCH8n8PAKHYZi":[13597,-7569],"sH4y8Xk2iUqEeHcj5p8HnT":[11799,-4535],"15RbtF7YCbCnpzoKnHG4wY":[-7109,-11522],"ojpLeERDnonV7gtDG1Ypdk":[12071,2941],"qSZcAMNoByfS9m91uaJKhg":[-8484,-14720],"rvTuM3Nd1eBEjK1PnGR6CK":[-9124,-2662],"sTTg6zJqgkutyj97UpTttX":[-4310,-3556],"iX7aaJfCDxPfqDtFpsnHjH":[-3727,11196],"n9QJkqG2zUnA7mTd6mtigg":[-7409,6914],"d9qZmRuuM8VXZknTBSn92s":[9107,2196],"9irG3EfHna8mav9CgMn9J8":[-2648,-7246],"iEAwPxA8xW5bYGTRWCi8u1":[12306,-7236],"gLMiWaeiMCfFCoivxmynik":[4957,-841],"iZQN3JeEWYjyUUea4xwwsY":[17699,-1040],"f5wrzmN36mLtb8LTdeCqqY":[-13017,1408],"vLthE2MzozujBEGK2psmSe":[-3429,11124],"rUBHJimwP84mwG9kVab5Qp":[4136,14597],"rXNynUgSZ9KteFw9zwMzHW":[12449,-6275],"bzRRQACafM49on7Su3Rgkn":[11034,-2184],"2qy5VaLJG5oPS1GGb84K7Z":[12798,3281],"kC7drdiLtR8VPFBWjG8owa":[11430,2462],"4a857H8p7umuFtC5yZF9i5":[17397,-1092],"mBKtgEFzpW6TjPnRNgwhRG":[4472,-1064],"3zcNEKs69BxLiN9NCbyacv":[12305,-7567],"gwXqY4df9JoLkVv1zNdZaP":[9653,1423],"gshC34p6CGMqrWEQoqkq1M":[9147,1673],"3WQdG39hrWvX8NPcegb88g":[4126,14326],"e1cYtypUjZNa23bdqme4fx":[14356,-6108],"7Bz1Z7JTS2DKZZVYox3NHq":[-1278,-4210],"mhe9TAVZuQXtPGTrCu27QR":[9798,462],"cJjHPg8NkasqWzicRD6dDF":[12446,2842],"mQ9Zo4qLAvpdBGyJJCW1iA":[9173,-643],"8BJ2ZSGwrX3YsseCSs2ShG":[3404,-4476],"uMSf8LcxTLRLdQKaVLPxsn":[4006,-5034],"jNYRDuSr7GnSoCYQw42g6J":[16515,-2316],"tw91jmQBsgiF7VYHhQVQEq":[-918,-4754],"ihPExq51RPZUafTvbds53u":[-7290,-13662],"pqrmNNx6Emrjz3ZrFKVkoj":[4727,-1323],"dHPnoLEYKSU6R4GsYjZpsr":[-10323,-11868],"bbcUufrErQv9oaMfjUUHfV":[8438,-3516],"25GXGw9sDaTLU4839EZbxE":[490,-7412],"byDEfve69xRFKNpmxE5NhT":[-10075,6870],"7PqS8QLS8JCKHRg6qMTATx":[-358,3148],"kZuurvwTVxkRaSJ9dfWRgW":[7406,12044],"fDtUHWZKN8kn6qYKscfX1a":[7716,-4647],"qNbrTDMtsD89qFrJvPXNzb":[12821,-3379],"45mRTutyUUAh16vvvcdpMc":[15340,-2264],"k7aenUpgMYDhJFRG2vNDvo":[-5482,-8154],"vAbv1gfgBsqjjFJY62HXPH":[-1476,-798],"xmhBBHugHnJ9xoivaxowBd":[-8327,-11430],"9iomXJxemr9GJEfUqWwvBZ":[4588,-4188],"2agBbfYfiidnBNL2s3L9Sg":[3539,5814],"cKLhrD5xPf83hZtS16EUc5":[-7739,-6951],"e1wcQCBmty5hkDZt43pcfg":[9845,3280],"v54qX8TQ3hjtvgmHisRR9B":[4244,-3501],"jvK3h6Jt384UPGodh9W6gg":[2853,6226],"sodG14psdjWTGqchHG49V5":[-9753,6904],"cCP43Dpg2BfNHNHcMBQDBd":[-3292,8855],"16YtXFTfwA5Yapwb4TbtAv":[-3513,8669],"187x8ECEmqXYotahr8AJoF":[-3054,8630],"8fumJMbmPKRb6qrRYSRrMG":[-2665,8601],"84t9i8MEHqjqkQebbrLQLL":[3714,-4829],"xaRAGtioqKQkj1ihNgSPPT":[11065,36],"96DqE6p6AdSSR92nvVzkxw":[2807,2581],"9o4Yi25Aq1MKs4K3A4e3nT":[-6485,-4154],"rLHVYzvABdygbcX21BMixH":[1387,-4425],"pY4XsVy3i7KoYvD6rjkEqQ":[214,-2507],"smW7eRCdNejKNR8G25Wosb":[-1985,3785],"2fzujcX5WUA7CmUPGFMDs1":[1381,5554],"7DDW1DHFvN8HpZ1gqzgXn8":[-6839,-823],"3RRNgX3MDGu1V7svAMbjpe":[-4031,10243],"2JofhLkZDRo8dBUxHsJx7K":[-1353,-6280],"goqiiHNX2TMCf8xVjzdNDW":[-2000,-7965],"pfMMJ4GZF7RcYhy4EuNHU1":[-11352,11468],"36AiJQfp7KBSikz46Mzqtm":[-4896,-3477],"2Xukkbdqp2NknE1U7ra8eJ":[9371,-3527],"dDARo9Y75VWmioUTYjUx8s":[-7013,9400],"bZNg8R8GaFWPE3rV6ck2eu":[-2241,283],"74zvBt23TD9AK3xBaNgH7U":[-1771,-1443],"voVGC39eTDdDNAzTzUxXDW":[-7395,-11659],"g4xQdUXyQqtdLLcnuNBWnN":[13441,-1201],"3KUY4mQhQTxL7TXH7Wx8Lk":[-9220,9927],"hJhwF272bkN54GfhiAp7sY":[-758,9346],"rbaqrmgPjdraNTvWqxDN6j":[-1834,-3703],"im7StmtfR8UJD2S9bjBjf9":[13925,-3926],"vJ3SZkyvDdHy5eRvEuRAKN":[12585,2634],"d5WvfG8q1wMmnGKu6s57FQ":[-6122,-3683],"x8y3j6RWWkXe898r2tDBbX":[-1704,-2155],"1bvoXb8drxyarqKahLoMZ1":[6462,12139],"bS9PeTPHnWPa92bcxGH8xx":[-6561,9885],"9vdxVjYpLGPV5AhJ4ftggb":[-1019,4850],"5pKNHu4pveTF6MnuTiHqbc":[-3317,4984],"mwSfzn5GtMZbgktFnKkDog":[-5653,6053],"rU9tbMZykRefMxwiKm8Mph":[-113,6904],"3DtNfpM5n2WA1LXm6RZTDR":[-2097,5169],"1EWL3WsYA4XKPV61R8pukb":[1632,5713],"wCCbx5MALsrKEACZoe4cP7":[-3812,8844],"vk1NZHUSRkHp7RGvP7CgAj":[-1840,8035],"dx5epNrqJ7Z8iGpDHajJ8W":[3284,2704],"5VZ75paTNFxHTipaj7UeB6":[-8708,590],"aARWrPEftDXYwQ8zMsYCWr":[7030,6520],"vN9Km9XfmqU8r7ADxTSU7B":[2819,-890],"m6PZKrSH8A8ZtccHBX1JuH":[548,147],"9gqquN7bmS7Xyes2uZSHY5":[-99,-1619],"xnMdvzM3TVrqsGPgN8bmwh":[-3190,5646],"hVNTfVBQq6q9o7J1EFY3Yw":[-2037,-4072],"hL4FWHqFDBs4JUefQnLG7q":[13182,914],"6P87XSCrmtEgAB8XayHZQD":[-6432,6435],"jDJr46zMS2eSx7Y3HB2WpH":[13651,1242],"5j2Z68edyN5XqkckWpNpsj":[4417,4092],"6zGNShkBLQLjgJASuNDQhT":[-1266,-3036],"jMfxjynos6gbYEiik1p4jq":[-8627,1700],"2bcX9cNKFQkXUBQyyAa2bN":[-1213,-1429],"dnCagFZJcuCv2ThVSB6EVp":[192,-5683],"bAe14XWaemGBkQftHTHnEb":[2798,5832],"1Yiv4Ubh613MWmam3Dgnjs":[-665,-6173],"hYkoRpHvHfrjQoWMWsxGpo":[-387,-1158],"snfZH54EChFuuS12jpzxkN":[-12854,-2734],"69wrZt3aiFZHSGYMauWZu4":[11826,-1056],"xiWyKyV9aKYBPXeW5k1PqJ":[13954,-6213],"9Tzs6Qoi57NWM2hyT6YNQD":[-228,-3227],"nUEuPiJLqGfVM9XTYaME8h":[-8068,3377],"etHbi1qTQXhioew22YCB8b":[-6931,4390],"sJ7ESRGigAu6xJhTVjXYfb":[-377,1542],"8rA84XutDuRcjtJVbXoD71":[-3603,-7257],"1NFvGWRUoRELYJCKs6k9u7":[-7204,-6138],"1pNqefP6bX3QHgFwgkKRWZ":[3972,1947],"vPNyQxDsLxxZuwuy38q7bY":[-2833,-6500],"qqwScDMu1wm7isjuaK8Y5x":[-6017,-2930],"mp6C2vKwEwHrVCUhah6wqR":[-675,-1072],"tCT6THkyWP7gP6jfLctTnj":[-14125,-941],"gwSXtvFVamYpXFNCxGYaZv":[-101,-1094],"4iLBj91LRwMXL7tefJ6jbc":[7360,4114],"bhZmGfM2vhei19wcaEVb73":[12103,-546],"uKhToo4SiCpKLVVMek5VfU":[14589,-30],"rARCWkNA1aUF6tz8pTUa44":[3066,3015],"5gZE2eWub7WTXSdzxJjweh":[1700,-2868],"vdnwiSgpaLJj6qoszj6KTx":[-4033,-5876],"qPnRkScAEmdHdqc1NHQTPp":[-25,-2743],"ij33KRyvGjwAho4kULChyy":[7109,12240],"iamfTDgRjf9VVpcutPZMPq":[-1276,16165],"np82TB1zz7tLtsRLs7dZXu":[-6402,4861],"uv3CTMceg3gwJvgWkjzJGa":[-1876,15735],"42pkhBpF8ubdUHBnRkKPas":[-1091,15836],"2szA7kQwyQGnjv8TqJp1Gb":[-6734,5106],"hpcvaPRinsL2j9CuinPeQx":[-8359,2634],"5UnHcNM24NdJQyt19gYbdt":[-2079,-1143],"t3QwJ7YUe9oEuRqujKGCm4":[1206,-2894],"fNwvyFamcQnJyRyi3DwSug":[2115,2836],"2VEcKPidmhXmT6Y6WRP1EN":[13684,223],"o3C1EaAwBQjeQ4E5Yxr2Bt":[2755,-2971],"g6ZcjTPTJRDxk2ahxKbqZH":[12188,-384],"py8eEKkBHei6Jvky9t8HkG":[978,-2628],"xdJVMfUXnvkMmkwnsELaK3":[1675,7868],"bkU3QUHS7AWEV5t1ncCnBv":[-5579,-2407],"iq1sYahnJ2AXTrYbufixyf":[-2657,5989],"bA23GAwhSFCqNBS7PL89S6":[-2587,6587],"xpS33fC1kEzPSh1EVEHhB6":[-5981,6239],"r2bwzu9U8m5nni8WLof7v1":[-3341,-12703],"dWQ387Q1JJyCsKPmSAkvbb":[6810,12037],"j9GocSTjUifP9umjq4nZax":[-7368,-14332],"nnxDN9WFfLs3NDNwUu1i9i":[14356,-4857],"3xms7izKFBdWshdqPCppyB":[13627,-4994],"fYAHpVcJHpnGFffn9VvUdG":[-6766,-5166],"pQxKYWbDdeS5Ge1HvURsFU":[6634,5249],"6LSzxX9fQ2HgR7EaFfApyb":[-14821,4344],"iTMNExD4LdmF21iXWZMiG2":[-5976,2765],"9irXaGBQiAVd3KVZL7RSVb":[325,13459],"6vihT1WUKBwH8eN3dS3Rae":[-4575,3473],"hcC8z9J8euHLT9wc9nhRfg":[-1097,-36],"hm694apBkoJPjDzFexoGoi":[-794,-146],"umRMzb6RfbUjYT511YeSWV":[-5197,2961],"cNSAWgFePFnwGmTKu8LaNq":[-3678,3123],"7oMCMbYVwyVuvasyv6mSPb":[-4421,3257],"rV47xjWbtxuvFkCSkxqZxj":[-3863,9732],"eJ7zdv7WajvjU3ktThfJ9m":[14482,3780],"5dDYauoPUinz9AJSHBkbm2":[-4120,8490],"eX25WjX3E2Vm6BAYBvJL63":[-8622,-2802],"dT73766oKFHqt95Nz9zrEz":[6711,572],"c9QRrMxkogZedGqcwFL1dK":[-10282,275],"gEfBTjMSrJVctxDhp6DpGu":[-3433,3630],"3hMzNioBshPqH7mHXKqdQc":[-7205,-43],"cNPP1q9mMXu8hwGvMwYk1Q":[14680,310],"a3aRKwgrEpRrmCTjCebyzS":[-4280,2076],"hvHXXPTFSipGXq9BLh5CGh":[-10524,-1830],"sTicGAzft4NGkoigf2BQBv":[2133,9649],"piXKVdQ3Ba4cobaXYxhHHT":[-9194,5271],"p4QSJ38P9R5agXuR7XBA3U":[923,-6907],"36rpQ6w6exV32k9d5PrMby":[10158,-3603],"mvzJyGYybM9cWzSA2Xiokw":[3465,2069],"aRKm4fvz6CfSWhD4PxAnED":[-10518,-11577],"bV5iAWnd1mMDJU7kHgQjnU":[-292,-3782],"bvyVzxuVPZJ26b1vYiJYbo":[-4678,9277],"hnr5QeKF5m2FT9sK6PupwV":[486,-4091],"oqHVuj5m65X4J2s1R8CE15":[15487,-664],"5wD3pHmR7MAJpW6RadKjQY":[-6514,-11209],"p4GhHhUPe3zqqg8CX8fCP3":[14689,-5378],"2WtXVmhmER1Cf17YWcpNPS":[-2010,-3568],"6cLA8DYE6ru2tNq71pnxGx":[-7006,8975],"2iq38jMnqevvW5DiYDxWd4":[-6646,7449],"8cUSttBgCD3XpB4Rq6NaWG":[2775,4676],"1DqPbfa52M65YL7A3r5UWP":[-8489,10734],"umEgbj8Fox1HadQepqyzbT":[8381,-1227],"qtr3crn6J6Uf9mTVoZCnjZ":[-3585,-993],"ptiUBXMFnx7u2XccJHLiUK":[-1815,-3988],"wyqxQEBWUfe538dK1oo55e":[-5821,-3565],"7kEZP9yPSKRi4DPmn3z7mQ":[-846,-6956],"qGRZnppv7g9oTT3sVVoPUA":[4888,-4386],"dTG5A3MoHP2YC1Co21AXtV":[-1886,-11772],"n7bGhBh6ZhhKwqzAtvJssg":[9633,-3733],"6mWWui2FEYv8PLzcP7qhpT":[7882,-3476],"sTDh13HERndw72RXv4f1n7":[9799,-2796],"6GDEzGfeaXSeEroxn4gWQj":[3631,-4994],"9AQqtJA8qGPpf9KjQciknp":[-2396,2001],"34aCEwNnNaveCrTXR4gqGm":[195,6101],"iiiZoQTPPDLk2FGdrVPM4j":[9242,-781],"cMURaNpefzK8xYm176Y6Pv":[-2831,2348],"jaRpHtvYRLnfe3CzBzoYwf":[3225,2585],"wtuWnhtbrDoEkmC7NDby8T":[1196,2469],"21hAUqEXgcTbRugRVker2D":[5554,4232],"r175uLvp34BYQkSwSo21EC":[-5272,9555],"8kn8o8PdG72CdzVk6LrTVR":[-7096,497],"1vqhFKBCpBQykFCKBWKUPq":[-1481,-9795],"1Gwm45RDYoRSKiuS48q2cT":[-12957,-5274],"2BkfdbYfj6jjiXcsPkxCXK":[16998,-529],"vhMtCC3iLprwfJjbbTYphQ":[-5395,4211],"f9HcY63chjWwrxQueYrxH8":[-13908,6418],"9t2F43r9CDo9SVdyA9MmuP":[-5646,8647],"4QBnCsSEG6zeRTr6XLm3Ec":[5747,2933],"wtP5ib9VcWUYP4uLA4ZEja":[1734,-1131],"gS7DwBoR2EknTWJfQAo7Tk":[1608,2223],"doeuKBU3iKy5fR9UvJkbqs":[6309,-2061],"3KVX2cHuiykQA3BRP32C4m":[9712,351],"aE8oquKqz96dQk5ACaLzve":[-1352,12258],"iw52fpXQoKc8rEUsE9RHAv":[4320,11666],"gaqgy8nC9V8LCL1HUd4B7i":[2640,-8009],"6rQMi1bTw2eKWRfMe9t3CC":[-2926,3082],"4mEeWmDMtXQe6cLdJ3Z5Ny":[13293,5811],"uUvj7YA6biJdfELAGzDUa7":[-84,-783],"aPqF8ATE2RKCme4WpYSJ4W":[-1059,8561],"3bv1gU8oiqMfwnvbAJJEh2":[-1046,8988],"wMzi2CUWVbMxda13EpfPYd":[-744,6321],"uUURnaXuUdxmXCiYdVHi6s":[-1092,17145],"7bb8zDQ76BQnHkxkYUvbZV":[-5882,-2449],"qEcphjJpEEUXLt8g12yQa6":[498,-1933],"eSKumsnoCNPJhJxkincMk8":[5275,-3922],"vA5aVbVGjpWa5JEUZk1XHk":[-6752,6008],"kJ8R4gR86qm6WuHZsMWnG5":[3678,-3971],"jrMvMySx65yKT1z9Agf9kJ":[-3293,-4527],"iEsoFZYXZ3TobNrXyTgaE6":[-8067,-4305],"hiBfQ1tCvvr8gUJV2DudSt":[-7087,-14066],"7o2Bb7gzJZjZMM424mBumA":[2995,1564],"ccAueQKfy517rZgyrYQzwS":[-2453,-9556],"rvYqgsE5njsEbeSDYyDfmE":[-657,16895],"5ojMPZgYMZq7qeEddWG8v6":[-657,16737],"njV3C2jk3e5seBCJFrXSpG":[1333,3254],"8abZLYFuqRHbLeA85TxK7P":[-5519,-8278],"dRda74pHkwuKhV7WsPFj8q":[-7946,4702],"1Dc9NV72YTWWJwrh6F44ek":[10751,-3261],"a46ZqAL4pBH6WXKvxrckUP":[-4575,485],"dF5q4SoV6rWkGghpisQQpk":[-4881,763],"wuZ9BXLeNAH4S8DMEkBUrj":[-3816,8596],"oCKuHNz33QhA7z73bbLaxZ":[583,9844],"8AsNJn55i5YS8QDPtwDjQC":[-1934,8958],"42D3s7hQYTdsJhAFtys1pA":[-1214,9317],"68rAYrkVD1LQkxUtbRQPYK":[-1807,10745],"jXaAmKH1fdvHYDUN534Pqw":[-4423,8468],"c3TSd1ZCfLn2fSD2Mp1LSA":[-846,9166],"hFcnMMaepBYCrKcuEZpFcu":[13298,-7408],"8fzvP2kxH7ymWZUjjK3mws":[-2395,15602],"d7xbxLKhK1i4MoSuHZH7M6":[-14217,5968],"1pdsYVaxzU7su7CJQQSwR5":[5067,1045],"9eUi2VpxhLpUEGgrWkRzEC":[-6550,-6653],"wbreak2pN7aoHKimFxgN2L":[380,8141],"kQAT6vB9n8B6S9zfcEpkK9":[1428,-2763],"bMLzWTy2TgRMkQt1Pd7248":[1678,-2230],"m68Vc9yhAJr2ziJoHV9ae6":[-7836,-15327],"5pKe1bxEt8KJ5HMG413rKL":[-9721,5040],"tLbxLc5WanrKjn8xLw3dVU":[5809,2445],"kMpwofYX4FrDGf1oAduE8s":[-2053,3389],"ohSsvhUXDxHyPnowCjykUG":[-6930,4146],"hGSazzwxCwdYsntkLbLfd1":[10275,-7621],"nEvMvJmCVaaeFdZVkbthy6":[-2506,10934],"bDZMBVKPWq5fZ96yxMnjrf":[2567,-5026],"hwTiCGc7JY3yyqZ8ZZjfv1":[-13304,-2307],"tLnsue2bwkqM6T1b31Eoba":[4894,915],"ugvEhVMiLWJrijDXUFKiw9":[-671,16141],"qez1mAmoFyySR3818YgqxH":[-10250,-536],"7ynamH7NtniK49E24maQPx":[17132,-1331],"fL5z5FuiHYhpNkW1SBT3R1":[10442,-2874],"oexcDMpWRs5jAVUidFQ1Pd":[10740,-2332],"rBsx4y9xSzLRoS6CVrcTxw":[-182,4853],"p2zsfEfGXRfdPSsSc4BG2s":[-4560,366],"dZ4rJHF9dFnhR2NJTzNAQ2":[798,1639],"aXeSFXX6VGvygnx7MdVWwp":[-16432,3387],"tz4jvkrCAKeXR2wBKzrX8y":[14849,2934],"aZMofFxZeKiirhw4fH2c9Q":[16556,-798],"5vMWRJzkskEVfEkDXdHMqY":[10647,-7347],"ta4iq3fkP8M8nrxUijF4Bp":[5508,2438],"6MbpgEVaTCWCYt8u3RST9L":[-8406,537],"6HsTDcapKzzqDavQKiwupc":[-10623,9133],"vDt6mQAULDkZHhuAKaNuPN":[2948,-2862],"kggXJq236x7JSTcUxvL2Ws":[4798,-2036],"6mMznH6mtR2JKbhFQTpPRH":[-7513,6277],"bajMRTYbtcQ37qZcYEjQaf":[15443,-4209],"k9Q7SqMUfqAvxMLiCoC7Ab":[-7984,-137],"rH1Rb24ieL8yxdzvWaydFN":[7587,10932],"s2aKF5pfWzXFQuVbCXZRYc":[-6368,-7460],"5wMMoFyKXWcEarGfL6Q3Lp":[-1942,-10975],"cmVBk5voUYdyftup4RoSXY":[-1802,-9799],"1EiaQPhKyKUicj9Gy8ekY2":[859,956],"sQf4f3SQeZahYQHjSscjX6":[957,-3028],"wzpjvMJT63M6YsvyNd4eJV":[1049,6617],"pq4k4qG4sunE12cVRXgQGT":[-4702,6851],"uv9iJN5RuZfMynK2MBp8RS":[-4969,9662],"ccyxM2M9Dk4FhGTFMek8H5":[-4374,11635],"whBmXwyQCCMA7A3wUQF3wk":[-5918,15242],"km2bJACtDJQt792h3w5Jvr":[-2993,-8509],"hBwZu8VXWARdJPXG3qA3pU":[-5063,1118],"bNrBgCC8k4ySXwspSkTkEq":[-4401,11281],"fkxtsc6GiZ8mYWjKYyNoCa":[5933,-353],"gVBydTb64PR7669rCiAdSv":[556,-5624],"r8SPuh4UvQzDXxRpeKaCXv":[-1404,-2660],"3tW2u2pbDJ1J8xS4hPJLbk":[10540,1848],"nNCQMxkaQ3fN1byVq6RZt9":[482,-3027],"7PPJziVJ8CEq5PqasYHQhm":[-4915,10025],"53JZyz8S2QFGfGWQUVGbMS":[2566,-3307],"xjyLpYEi1rHTw5kUKGeSra":[1274,-3665],"ghVTqRyxyZUHKbqcaPwZxG":[1155,-3291],"k5dKXFbZWTKf7bU9swtJt9":[-1053,-3358],"bLUYbg1AZ5dZLiKxqdsoMs":[-2948,13683],"droh3ekBgp85eDkeigz7Hw":[-1751,16188],"9XRNT2oEA83JZH8j3eg9GR":[6369,-1846],"hsKzxTjCUJpcXBr54BUdD7":[258,-3323],"pCJfAVyx9MZdWN4tihZigc":[11216,4390],"hJ1Rh5gqbH3daBFR72QXQr":[-2567,3642],"fFBm5yLfFVMVTfKu8fsedi":[-7110,-14882],"vDefLGxQfRWJbTyqrZF3TN":[13046,-4801],"ax68HuheQpMyQmSdT7AZSs":[-16786,-128],"4HA9dGrMdH6vB6AgmnZpX4":[1946,-3083],"wvHYJh8pU7vQG7ZmHFBY3t":[-6939,-15128],"8xn5EfQEYaACYuMY6o4c8t":[-9586,4913],"pngEFK2NYfMib2AHFkxd5g":[3075,4714],"aQ8K17xAHncatk3bPBMamm":[-5765,1026],"3jpiwaEW292njfDN2YbBku":[-3418,-3422],"cfbPJUAHEBgPTnYH8kmiSF":[1927,-2453],"ptfhJCacDbCwKu1U4LjUxY":[-4776,-11382],"vVmfURfu9SuNNdQh8FJqW1":[-5479,-8600],"bddpjUwHkhrhNVZXgvQgHg":[1904,1191],"gNHB5hw3XgXrHGKLbV5xv3":[10762,894],"6d6x23KTTFTUCa8fqZnbJp":[10608,1658],"gtFCG1XPNQeF98qK39taM5":[-4818,-8934],"tbi7CNeBzPQRFuyZQWWSCg":[-2222,8776],"jY5L5QTnj7v8Xob4t2oEna":[-1404,-2308],"4X91sDEh2cxR2rTRGpf55c":[12177,797],"8PH3LBZXsxES1Wfa8NELiB":[1091,-4122],"vYGjrhdYge9TQ37r1Ne3gh":[-6773,14564],"kFh2eSCLkKkNecU9sWWEtc":[-3648,2386],"h3kfiP2vBGRGy3wDVcMRrh":[-4270,-13018],"oyLWhJ7mVPDNVcny9JHstw":[11002,291],"ra7FTW9UX2HnVNHyHVr15v":[-3678,-13403],"gsQpLCVUR8QBALHzDRsKPy":[12506,-2380],"rvSsAQNSdxJwJNv99Yrf5a":[-15120,-1100],"pmcJ3e2vQQekYJhTeLqRVV":[246,7022],"nPZT72LNd6zggShQ5wKSEk":[-1285,-11495],"h1JERbtvRQVVX614StKLr7":[13673,-3183],"szVbLZha69aD2KQ5Y1Yx2Z":[-4469,-14251],"nXmJamWNgWVCngNct6f1R9":[-11734,-1376],"sbeyFmy6a8Romx842rb9jy":[13338,2349],"nRX7Pn9oWhAsA4FWroev2m":[-2335,-6525],"ndvaHghVkLcNUHwFfxQkaK":[-6782,3841],"sUJQTLKU8ftUub5dX7cpnf":[13507,-1921],"w431pzM3GoacybKLduqTZY":[13364,-3317],"vimwWR2fZzd2ecMxkvsRdE":[-3384,-11235],"4KLPJiD9NfUMSRLMGXFYeu":[-7452,-4958],"cR2hDYvEWLv8A5KePZjqih":[-1100,-2657],"4sqoVdg6qTjf76yfrrxp6s":[12806,-2470],"mAbXXmb7mcFDgzoapySdvV":[2507,12848],"jEF99KpntCtsTC6nSsXQXT":[7514,3077],"4MeGepvtamGJjd2PReA7Qg":[12993,5588],"iXmdnovvwTmexyt14XRQap":[-2696,-8971],"8VLF7wDzFmiyNVLjEvL96S":[-10194,-10924],"iETg1avQFwCxmRRdKyYC1V":[12520,-2076],"h95WyN3acryykYGVySpTeU":[14648,-5629],"fynZ2x4mTKTHWrJQUSy8ky":[-9918,3725],"xf8iUujLGLnyB4FmYABMCo":[-203,-7505],"7oZrLPH25JrHneA4MYKPnA":[2468,-2402],"bop6efMbPm3PVq4W1zqAH5":[1065,-1277],"pBiCgfTnvcwx1M3RJ11FSh":[-11690,11329],"jupC8PZaUYg3eYickiBTC6":[-3524,-1884],"faMVAJqHTcXW2zEYf9cyWH":[14062,-673],"nQhkYktHYvYwMWmqjsFBsh":[12224,6676],"rDSBsgx4uhMRyayZi1cGDu":[-729,-3237],"4wEzVx3BxnPKTQN6RiXb16":[-3180,-679],"mcsGqkpBeVqT31z6Ttm3wp":[-7999,-1448],"j4wpSJqne4avsDQZpJRWtG":[-4009,-4367],"asgChoD2aqoAwrcQK6t4uE":[7497,1842],"83SVwArKCEtRR3BqDTrotx":[2370,-3035],"sY69rvxNqWfZwjDTMj6KhP":[12002,5731],"2EfNL95eEVVPLjCEcgKwip":[771,-1000],"vr8vsK48EhjuWjgifLY7qc":[15366,636],"38goaVqrLR1PMsGVfWvZMd":[14198,-4013],"2iLB7quUiyrbVLjR4g2ZXe":[-381,-2983],"u8k7hCAniGoWwBj2nGi7Un":[13606,-5994],"tgiETfdjupvaSrHLEwzn5j":[11146,-7687],"nCRKNLnXr7aferHRpUMmyy":[-4449,-1411],"7u9fPD8PCwxrxXQUGVtFiC":[11689,2667],"azqNdrtpbCKnvyUfZuK8E6":[9994,873],"swg93CRXdaZTeQEy7sqNRq":[12612,1785],"qGgjm99Yk7E7TSpKY1AzQ6":[-7210,6331],"3sshTEShp7pzvRiXFgyMtX":[11303,4613],"qso2ohD42dDkkgwq2QV7sf":[1195,169],"kQFPnmV6NJrRMHWaCsjEUu":[2223,-1184],"oHa3rA12dVJgRsK81KWngP":[-5210,10142],"gsiw6zMb4jKqXWGVT7pTHn":[12194,-222],"47d4nrnYzpjNV4vzNHSQgT":[9704,1620],"qM1azFq4wKWFuZS4zqqPE6":[-2995,-8833],"9idYKEfWeXc3RTEHrnonv3":[-5424,9938],"fREqikvns85fiqMghC6dDo":[-5745,9052],"hv2XXmgHRDrjeTXC4cdgu9":[1965,-5565],"pg27jQqGxd6gNJEZL6cjjb":[11740,1508],"1HkS6WjcWskaVEGWWTzHcj":[-1202,9696],"jHahs648Pn2qTYS4SU3BLp":[-6804,3957],"1tUWPwdiNCT6RrsS5xsoLv":[-3276,-13347],"avVspqLLtJh3Rns513vofc":[-964,-6353],"iPwu3fsej8hex82Dn2jYUy":[1305,-3934],"w1hx2vXJSaHdKdsDRa22tH":[13830,-6695],"cSjExjk8LPPaz1hrw9TPFH":[-2564,-2970],"3z4yXde8kH32JRy5ChTgXd":[1405,-9267],"pwZjnqiEBD8469ihzhM8v8":[-8868,4739],"4HXRNSCSedxTmCH67Wx4Z2":[-8804,2569],"iHPF1mjRruTBctY1AS2YpH":[11989,2744],"tUFKFDUu4eAyKH9tmpQUMt":[-3099,-1552],"vRPBNFUproboyuDoaxzwVX":[-12743,4169],"3ShK9RQoNMJ4boPRuZjrvi":[-8925,-2807],"mbW1fgW4wFz7WvR5yiQN2t":[-1423,274],"9vZq9xgcM9bCFupXrpGB3j":[3683,-2703],"rY3ZUn1mvp9NxCRe1y84nr":[1357,-1007],"s1nMezG59bejDBpDY6BTsZ":[-3064,-12285],"89QcaNagNrSVfSg6wVBvmQ":[-3801,766],"vb36aUyuT64jK4YKMCWXUL":[-1994,-2679],"kZVCQxbctTiahsWyPguTtU":[-3906,7649],"krJoWZcVcfBXVNgBUWxHig":[12497,-329],"gfLQAFehPcpoNDKf6MNLn8":[-4646,-11972],"4SHiR33eP1hCmdUu89tU9d":[-4760,1035],"pjXrfWN485cPeuzNy4kWpz":[-4641,-11678],"gEc3LtGsTZStDhPhK7ccV6":[-5050,-15443],"9k7RfFcHADFfec4LCR6ZGs":[-1511,-3431],"dhtb6VDte3hTeK2MwHegXs":[-9563,-12551],"6WoWjrCvTMMCUkQn9thNXv":[-5024,-15268],"xhSrqVnHggwPsN1Np4nPNS":[-836,-2925],"rZvaL8L13fUebQLxNYaDBf":[-6495,11438],"oVfcjY2EhGzi84c9GT1iNY":[-1640,8577],"knZnaXoCjuuSGpvCsvGpLS":[-1481,-7566],"weA4y7cJsk1SV1kMzAijKE":[-5571,9495],"2J86P6ov9aQbKCdocoepLK":[-8030,-4522],"3rCSYLpkHYEMvL4wUpBE8F":[-12306,-4209],"uD1WyvbR1WWTtdx4FYTvY3":[6104,-5368],"7RTBdPZFxbSVFT8yXTuB3x":[-5455,-5664],"bWNzG5ibxkcUgwXh8FDMDc":[9405,-4434],"fFBRTft9Sc2p4sBQRLAUs5":[8587,-800],"jZEhdvTLU29XLfjiYT9RJ1":[-586,-2943],"i9UntHrpETBcvDvV7HcMAi":[-4533,-6195],"k7jFZPtSuJ3KXcDfgRTxrq":[-2408,-8939],"u5WXCMYNBGwigF2v16SHwZ":[-5497,-7869],"sdHdZE9Umv2RCMYhcMfRrR":[-9336,-3035],"9QMm2aW3irF1K9ZQZUUiBz":[-9538,-2911],"4dbnrhtc2sqWnGn9fVKaB4":[12494,-95],"4TMmfkgiEnxZurU2QZWGrZ":[-3188,-10802],"duZjAt12UwpHQ9o57uTxij":[1842,-4100],"1LHzbS6Hp1ae3BsNcSjASs":[13252,-6822],"iy5eksWYxnNa62VyDoMD43":[-3873,-13283],"f97kguf9PaZFSRRGSzgBYN":[-8107,757],"aQuS1mz3PD4CyvoLsvW7Rw":[-10616,-1517],"gWRWFDXLBUgT8K9MsEZVYM":[11374,-1616],"3Qzwm6GguHV3zJCA9xDYkb":[10570,-7677],"uLkz6JQiFqkK1bNsm7dqgm":[-2156,-10523],"wPkfkp2R2FYamNwf6aj1kB":[-4910,-8036],"hHpuHdQPdoBd1XDGPFGNWP":[-5499,2959],"b1rovRpraMYo4FVZpb12Z2":[9789,59],"jDACdFzLDi6vMzLL3AvySS":[-6086,3646],"hsRvA1ZfARhbbTVqRZukNp":[-3189,-5065],"wS6qC8hRXAb89J46SNcgte":[-3715,-3202],"mgbc9etEGEXdYnpA34srf1":[-2280,-3620],"nz2cXAfjBo3D9jg1jPiXbv":[-2744,15718],"vz9eThcBPDDc5kvnWMnndg":[788,-3765],"iW1vvYGqTKodX1WM37wmNM":[-4623,10072],"6afgb44FDyLqsgKWz8E4Q4":[-5330,8609],"1Sg42cif48kjHzYzU3cTGJ":[712,-2840],"7Wvc1bpgxD3QdjdHDMs6cE":[3943,2298],"15exsoWLyhpR8WCCTqiEXS":[5117,214],"nd7LmXLErjwRYpQPFhqvd2":[-5938,-8188],"fCjY4kGWoig5ewAA9id6a9":[-14764,4728],"kgKuhGrJBTS4hmULLvbFzt":[-1655,15189],"17comKMvC9TEvnoxiWZPWF":[14777,3713],"tj6MMDaDSygVU1GyrQadky":[7872,2294],"pjAixe7MDTvLwAqSYW1AWN":[13935,-6074],"gkmGCSPaPgu9FVqttYicNG":[12404,4438],"xzTR3fKfs99iSMtdfX1jAf":[1023,-10991],"h7rcRo1WwbqA7AUmXvcuWg":[2871,-4148],"bjZFWHSprqoMwGZPxDJT8j":[-1685,-6399],"cKo9K4RvMJdeYrnirLGs4G":[-2105,11558],"fyQkrD8fPpt6K1KjPYbJqH":[-6807,-13205],"sCUiHXcjPyix4aaeq84i8u":[-4562,-1943],"48BMynYEiAUiiqhapPauL6":[-2310,-5887],"niz3xcBGkirZWCD6T1ytkL":[2133,11090],"tV6ZZQMAyGHaM5ieNDYSXN":[12742,-5101],"gZwABwaajFzf3GiGBchncD":[-4022,10797],"teycreJ42jRu2YkCyiJ4bk":[-2798,-1902],"mTEPcmW61jdmS9pLDqty19":[-3230,10370],"tFbckUpFncympYBTgMyrC6":[-1053,11503],"tTbfbihUtsYkXs82SNrPfs":[-5008,4948],"5v6SyFEE46FhPWP5CAQULv":[-5818,-12672],"1iG2x3w9Z92oLVHXUoi4xB":[2137,-3005],"txeehk9Qct8GyguEK4B1Nk":[-160,9458],"jAPemdMLC78TKm4JZr8YHT":[-4139,-12858],"cNbSXdsQJw2JHLcxHeEKsJ":[-1178,16279],"eXJYM1qXzusgKXUK6rHrHt":[-1581,-4570],"567tvG2WqVj9hH9jLYo4Mh":[-8479,-2379],"bZzXc2qXpqgMbUFtF1vWBP":[4415,6092],"nKeGkCpMSrEwdw6VnV99nT":[-2851,-3954],"j1fsY85LVJRkAPmGFE2Txk":[-7254,5775],"xoZtvMLYYoWqXiBPPcceE8":[-8008,411],"oi2gizMwW16uaTMSHHLq7X":[4276,12405],"dsA2SANTRECD2Yh4SszuZQ":[-9569,-2756],"2Tn64VsxDAJwEjvyC4Txa5":[-9948,-487],"kfegAowXyS3ksSNPgLZb71":[-6861,-4734],"8Ycm32AEtHC3SPJiHBcP8A":[-12097,16051],"kM9qSXMU7FMYRcBXhk5JMx":[-3113,1513],"pzFXuvi5yt7xXaCby4uzBH":[-2989,-8982],"wgYZjBrUJJ66ckH7Cy9V9T":[-7024,-2282],"f5e96NwKYXhZuKQdSngBNs":[-6920,3279],"rR1sKdok9AXVuUrVxqzyaj":[7104,11928],"wWgWipTrbBQPQ1J9965tGm":[-9267,-2798],"r4FVNf2Cr5oAyREt8aWMk8":[-7065,6846],"bo7qKM7CLKWzzLPViZXv2D":[-7205,-1777],"k54JrTQbWv9GhMEHg7YUge":[-4912,-1003],"uwHa3at6hgwhfRcZrvjXt3":[-10784,494],"jdi4GjeQ5ap8ZYQRtBBRWC":[-2064,-447],"njwbAJHbAgdc1Mhpu4Wdtj":[9012,-3024],"fy9r8cF8BkvPyo7wbsQAzY":[4908,10291],"nPz5sqYKxZs2qxZfordaQS":[-5242,-14297],"5kcYSjsHFhjiaNiE9swCJS":[-2651,-5198],"b1EF3hzwKLnXcStCPVvjDi":[-10315,-1550],"8CydbMS7a9Ex6ndfUG1pPB":[-9871,-2750],"fJ8DAatFzEFGStuVQpguYE":[-11821,-81],"uAgQtVGhpid2KxpGe8Kzrc":[-2949,-13155],"ay8MN3hWsyXLd9uRspsV5Z":[-3104,-9343],"23uwK2ESvCsDogczVZ7Yzj":[-1185,-7824],"mAueYH82zffSpqBiZ8n7fX":[-12463,1217],"6QxWS8eRKu32GuRMGtoz3F":[7241,-6813],"cfdAHg8Zzhk2FGgNfm2JBg":[7812,-2628],"fGUkTXuHUxHu2wiw4tgz4z":[-1774,-7255],"ewaLZQyht9ggQdKoUbfXu5":[-2678,10159],"wqyuHtFWLD2gX4i6n9hHj4":[1,1263],"rNL4Xbdng3Too2GEE7itBa":[-2065,-7058],"diB3usUcaK9V54M8soLsKb":[-14110,1772],"7tQzifDFsZxfcRuXu5muWn":[-12799,2405],"7heHWwoNWofSseDcZGsLyj":[-1915,-12032],"pkFkqpRvKvWUmZwuLNS1om":[6282,5],"6PiBEVqRfvxrrmpDFKxyHp":[-4139,-5760],"k5T5E3KwdnZ6mGSJmy6KGp":[-7361,3153],"nmrnzDicUCUFYkp7xPW6WN":[-355,16873],"72wxU396pdVnQT9LEAe4HJ":[-4807,4207],"3G7ejC7WiCRMK82kjemUbE":[-5496,4100],"tazS266YaGUnQFEjLMhYox":[-2011,-5937],"gL13e3z8dMkBuxZWk3KKUu":[-12056,-331],"gpNZZzpwywgevmjzoK7nV3":[-3398,-9892],"if9Z9aL4g4TygUDb7V7rQB":[-8469,-1756],"9zwfLU7K9paVDAyUmNfv48":[-1686,3495],"rnKzyKd3t3B6BiTFq2CEEV":[4626,1906],"nUXi3D2iQgTRNbSrM1zTKB":[-3485,15117],"a97WnVSTTtSwYogTYtphS1":[-6037,11613],"4KgwuSG3LUQayJ3t56wmw8":[-5534,-14021],"ixK22ZPKZt4JrPowHaXFAW":[-593,-8436],"kjGoPVhCfKPMRvMCvn18Mu":[-1514,-3961],"kt87cwe6DsfVn2zSk7X19h":[-5454,6341],"qCf9dZuRgWunSK7RFNKkoB":[-15116,3087],"bp2VcaoY5Kh8GXCeWTm7jJ":[13325,-2440],"dZW8UR7W28TFF3FA3nbVvu":[-5557,7083],"74pLFKxSyBXUwsbjo9s24E":[-3997,1111],"fWsXUctU3azeNuBnJryqGw":[11406,7681],"cXVdxkDU5SR1WreFjU8rU5":[-965,16536],"kj9XNidjfYXA7kokeyfhRR":[13908,-6407],"5wNEkWKktfgRyp2qyZHRFJ":[14498,-4004],"5sznDY7vzQXPewNnm8aRZd":[-3372,-13727],"piL3cCcqTUi4cvgBW9e4Fs":[3141,1907],"6X7ByjqmfCXuAa8ZxTvmZR":[2263,-4884],"51LeeRudCdCMDhvFYyToEi":[-8474,-1187],"6xxjPjKwxgL3DJk4WQo6ii":[-2285,6460],"rq4QMWj1w1rkSHsgWSqWeX":[103,5442],"ibu7vGbdfLcMDfqu9EfjWW":[13657,-3566],"5vTEyvV23CgXbi2d2TdVyu":[3311,13763],"pmwBPK112DfwB3wV3RDWuY":[-10841,-615],"bdWTE2Z5myxp9bu1p2Giwm":[-3056,-13626],"b7zEp8fG6LkAZnd283ByPc":[-7084,6493],"g3yyGdiTtqPRtZMTYpGpa7":[4129,-5717],"2S9Gt1UTZHdLz3YfeWHNFY":[12901,-2002],"ppvMVV1xAXn2Bt4wTJPEjF":[-3468,-13612],"umPRfgQQCvjHtnyH1fBEJ7":[-15511,3977],"aaCSEiso4VPYE39F5AHoqn":[-5873,9362],"qpktvticcMN6fLRYKuVtDe":[-6849,7092],"mcEU7r47scexJcLLc1C44M":[1008,5548],"vT388W98xnBJoPBQYszCtT":[1376,7961],"ejm2gigMRXKgC1GQ3wHWWJ":[-8436,-12702],"fgq8WHZrYmFinAyEMLf6L6":[-14929,-4103],"mpHzygXkXbmpUdRhpwcNAT":[-8238,-2508],"ppXvsMvpZ1V4rPtxLw4up9":[-11734,-2639],"rqK3mjrQ2EDr69ZEGNwbBQ":[-9356,-2421],"2DRQQf36wg6kEVvroyokzB":[-9561,-2309],"hfh8M3ZmDbhiGyAJfvBCe5":[-9312,-2531],"h9EFaE4kaMxjhnGYoNKFA1":[-9380,-3158],"pSrkhyqWxhWs129iiP7LR8":[-9203,-3463],"hKG4V3Vy2bncxH6Te56y2m":[-2246,-10761],"cMoTvKmjxwKUPvEA74Rqrt":[-3571,-13283],"fxPzrvAydTtDwD3e7Ttx3L":[-1750,16046],"iH6q74bCgMABCWimA9fXBD":[-8899,-3482],"w8hVBvMrCaZHZMxb5ryZ3t":[-450,-4947],"ckiB6PgL1JkcnaAbLQrtAW":[-11245,-957],"5HBNJzB4eNTpzjipg6vtmG":[-11143,-5497],"biqUaYnmTFzJpqnUWBM4E9":[-457,6631],"nJeF9XP64MSyMNXXmNWWD1":[-6479,3933],"aBc28UXURgFDxGtc7QWb1z":[15244,2631],"kZEG2Rq4anEMVGmoma23n9":[-7618,-47],"fkqjNwqWecdHugcTPUza6u":[-2120,-1799],"rt5Dborhj4HQgQebddPzz7":[-10905,-5173],"2P5hwH9GUN9vMr8aq2CkuP":[-6230,-12910],"qcvhXCAJbkgYes9Jx33Kk9":[-3249,-13070],"7GgFt4wdMneSVGFmz3H5Q2":[-3356,-13497],"c5gzZszXYcN3Gh2TGw9cdx":[-8661,-4213],"iAY6u52uZDTVZU8fZPipx3":[-1173,15683],"gJHofoj7kntUf9pSvRE1te":[12737,-6156],"sZeGFPqJikeq99oRR7rwHY":[-10364,-12103],"aqvZjFvvy18afGq6fzst9k":[6737,-6852],"8fmJMVHfkLpBNANShyumsm":[3524,14608],"1x3Vtja7cTDsgkEaDZGxcL":[-11490,-7800],"cP5GGBQUzgvVgcQkbs6Fbf":[15083,2784],"e2jAiDQpEN6rrCh9YTRJw6":[-4380,9477],"6XTiS5ttz5S7PWoqkjeV1k":[-2455,703],"bVWeEgstom3YTq4X5kJCL4":[3994,-4432],"rwj8hW8hWdWcQWMaoTKd4J":[-7993,10789],"kkbxKg8gBVY31x96T9fgUv":[3944,-2758],"uYN5vB7KGVSeet7d1b531r":[15823,1426],"55uj4KyNEn1EXa5TqXLogJ":[-5680,-930],"51S7eopxCoEhd4mxGrAWRM":[3954,-3527],"x44bzbbkbzB9jAz7K88yu6":[-4421,16026],"n8aqA65p2rMJXPKQGJ94cE":[-5831,9952],"dbsDZRpY7HYSSA36vb6hoT":[11389,-729],"ghuj7nKUbQgS9sYAEFdTkX":[-1627,-11306],"de8MD15j8jdsVdoSNsV8eX":[3282,-3014],"fnLUVU8CqaYQW1ijs97jyt":[-2886,-5537],"vr9d8A6i5z1yjaTMkKuja4":[-909,3260],"vi9mSkzSyifjPauGSGmngu":[1713,-3489],"imykmnB7GttD72Z8VwjGhb":[-5028,8496],"wAkMuxAiT9cV7FkWBWGstu":[-6428,-8705],"28y4JsKJocZaXyXVteWasv":[-5098,-8313],"aLHTCrfLo4Td6anRHWd9ow":[-4615,10619],"jAVEzDHi7shbEKaK1v3R3T":[-4913,10536],"8Vpf5u7je4An1C3hbfUQfA":[4278,-773],"edkxVGRYNN6Qw8XVjkRqtp":[3205,689],"i91ZZ23F1NvTvMF6vD4ggC":[-5893,-7886],"gRVnzrCE59pKzVntUKdqyH":[4026,-1829],"7Vbg2rawDQcYGNo9oPu6Zt":[2519,-1109],"24Aj9Rwbbm97QNvYAcHDTq":[4246,-3066],"rxUBWVX8318dVREGveGn1P":[14572,-3506],"dKebhHZT2SVrqVZxSwiFSu":[2564,-4215],"ajuys67MUiooARdhox31GL":[-5195,4543],"dRUxkZMN3A5XN8gnwGJ1oZ":[-6046,8953],"9jrer3JgaDH2XKwXVoydxC":[-3989,1587],"pzYqdqcNWvAiuThFc1dRg5":[-12897,6149],"cyCYa5aWHQLEhRGmevTGRe":[3219,-2434],"ajknVgnMsKRLHdXgzxWbAh":[12973,-4307],"rBAM5C61AZk9hRrsB1bSKo":[-5837,-2024],"sejejAZKwEVsqncEhAnKvZ":[-7224,-16106],"hkwCNTTLLjNvyhnaw6Xytq":[-7557,5794],"rHszEAmrth6LwNHGvdNnap":[-8496,-1345],"ktwGdsqSgfSK47sBgEDYs6":[5947,2206],"dr7Ffq2JuTsxxRhhfKrbaY":[-5856,4063],"cxKZ6UzZu8un1i92ZvJg9M":[-5175,-15617],"bDqQodPnRp4x54CodT8wE1":[-4320,10721],"7Hcxq9mCYp8HB1FjnYdjsq":[-1939,14635],"1ZHuBQGz9tVgoYeVpiiUPH":[-8084,6114],"oCYrQHaoLNyX4wj8Nc4TjH":[13853,-6962],"vJML5mp6TKJ9gaXHZsLJj1":[-8368,3249],"oZY4JrZGrPGjtLFx7RMJnu":[4205,2512],"vG6QnDGYzaBWFm4T5txzsu":[14417,-2324],"bngQ1C7cwopUxZ5n9z7hSq":[12099,-5135],"cMjRD4kaw35FRMQV62U8Ke":[-6067,-7655],"rezvCGc1wM9htoMpwtncvY":[-3685,-13729],"1XVnM5WJHfaCqYaXsyWV6d":[12147,-6423],"qetyoadMndoUR1Aa8MAeHq":[10694,-1354],"vJkmQF9YVf7VTPhfjF4E9R":[-5218,10412],"pNNaG3UP5teTgS2Cu4AeRB":[-5904,3046],"4TCMa5bMVF4PtTAxbZqSVk":[-5674,2800],"3yxs7ovtMvSFD1Qy9rsu9W":[-5471,-10659],"cHJrpwM8ef7rNTJBsSGYAo":[-2648,-8150],"1yAqCXSUEUQLQTj1NGBzRR":[-653,7961],"oa7diQytLwAU9on4tDcG1c":[-2981,-13365],"uykjhhEx9qx673uGfLbjwS":[-3334,9922],"4xkUJEPAxZoahFjsKbVFR8":[1103,7002],"2LLX6Kqs1vkYNSM4BQo4BZ":[-5512,10053],"bmNwstCz9xZ2DqgGaXY91m":[-2103,-9786],"4bBN2cJ5RLB8PXp6PeEzED":[12379,-4395],"td26nuYuwWcv3YmNU8Gsau":[-7439,1610],"prndqqz8SywTbZusrv1dPF":[-11435,8624],"u71cxizaVd5d8dFmZpJGTV":[6394,-317],"xwKA8nyvGTtA3ZS6kyT5mC":[4905,2416],"fmjDP39rp1129BnS7U51tV":[-9760,-12121],"fpK3DE166EBPFbSJoG3sPC":[-2055,16105],"rUQtxivUapn8SqCTpycrig":[-3889,5130]}}